[
  {
    "conditionId": "0x2745c38ff0617cb345c1d2df19b4f74ea777508e07411e88eeb6ab3affcda2a2",
    "slug": "will-bitcoin-dip-to-35000-by-december-31-2026-744-877-748-219-467-465-646-211-122-947-537-552-555-361-972-954-635-887-657-996",
    "market": "dip $35,000 bis 2027-01-01",
    "family": "touch",
    "side": "YES",
    "status": "OPEN",
    "entryTs": "2026-07-04T15:01:42Z",
    "entryPoly": 0.125,
    "entryFair": 0.2281,
    "entryEdgePP": 9.44,
    "shares": 800.0,
    "stakeUSD": 100.0,
    "feePaid": 0.88,
    "markPoly": 0.125,
    "curEdgePP": 10.95
  },
  {
    "conditionId": "0x1e5564c1a2a6839cc2780a889437c63786a2c2ec5e95569b710ee659a3e8baa2",
    "slug": "will-bitcoin-dip-to-40000-by-december-31-2026-593-522-842-874-931-776-991-167-531",
    "market": "dip $40,000 bis 2027-01-01",
    "family": "touch",
    "side": "YES",
    "status": "OPEN",
    "entryTs": "2026-07-04T15:01:42Z",
    "entryPoly": 0.23,
    "entryFair": 0.3144,
    "entryEdgePP": 6.83,
    "shares": 434.78,
    "stakeUSD": 100.0,
    "feePaid": 1.61,
    "markPoly": 0.225,
    "curEdgePP": 8.7
  },
  {
    "conditionId": "0x903a1387e6414be5529efc8f7757e30371e6698de9d68fa4ce33252009db69ef",
    "slug": "will-bitcoin-dip-to-30000-by-december-31-2026-971-191-116-343-999-758-299-813",
    "market": "dip $30,000 bis 2027-01-01",
    "family": "touch",
    "side": "YES",
    "status": "OPEN",
    "entryTs": "2026-07-04T15:01:42Z",
    "entryPoly": 0.1,
    "entryFair": 0.1718,
    "entryEdgePP": 6.48,
    "shares": 1000.0,
    "stakeUSD": 100.0,
    "feePaid": 0.7,
    "markPoly": 0.105,
    "curEdgePP": 7.33
  },
  {
    "conditionId": "0x10492aaf796455be720f0fb12576f029909d3c2aad61c38811f73b15b7690fe6",
    "slug": "bitcoin-above-62k-on-july-10-2026",
    "market": "über $62,000 · 2026-07-10",
    "family": "above",
    "side": "NO",
    "status": "CLOSED",
    "entryTs": "2026-07-04T15:01:42Z",
    "entryPoly": 0.61,
    "entryFair": 0.58,
    "entryEdgePP": -5.73,
    "shares": 256.41,
    "stakeUSD": 100.0,
    "feePaid": 5.46,
    "markPoly": 0.65,
    "curEdgePP": -6.06,
    "exitTs": "2026-07-05T11:10:33Z",
    "exitMark": 0.61,
    "exitReason": "converged",
    "realizedPnl": -5.46,
    "roiPct": -5.5
  },
  {
    "conditionId": "0xe498447cc887be42044835ac88ece14c34a158a3e6f5e1be07a89629d7100b61",
    "slug": "will-bitcoin-dip-to-52pt5k-in-july-2026",
    "market": "dip $52,500 bis 2026-08-01",
    "family": "touch",
    "side": "YES",
    "status": "OPEN",
    "entryTs": "2026-07-04T15:01:42Z",
    "entryPoly": 0.145,
    "entryFair": 0.206,
    "entryEdgePP": 5.08,
    "shares": 689.66,
    "stakeUSD": 100.0,
    "feePaid": 1.02,
    "markPoly": 0.175,
    "curEdgePP": 5.24
  },
  {
    "conditionId": "0xbe20fcfd54937c2a48a7b8521ca349e6a2c4373566328ebb950a8c35ab1be3d9",
    "slug": "will-bitcoin-reach-67pt5k-in-july-2026",
    "market": "erreicht $67,500 bis 2026-08-01",
    "family": "touch",
    "side": "NO",
    "status": "OPEN",
    "entryTs": "2026-07-04T15:01:42Z",
    "entryPoly": 0.435,
    "entryFair": 0.4147,
    "entryEdgePP": -5.07,
    "shares": 176.99,
    "stakeUSD": 100.0,
    "feePaid": 3.05,
    "markPoly": 0.365,
    "curEdgePP": -7.09
  },
  {
    "conditionId": "0x2be031440c5a571cd4fc3e05e2478d98aee41c7a44d10d3c5e6a24e38b30fabb",
    "slug": "will-bitcoin-dip-to-57pt5k-in-july-2026",
    "market": "dip $57,500 bis 2026-08-01",
    "family": "touch",
    "side": "YES",
    "status": "OPEN",
    "entryTs": "2026-07-04T15:01:42Z",
    "entryPoly": 0.39,
    "entryFair": 0.4667,
    "entryEdgePP": 4.94,
    "shares": 256.41,
    "stakeUSD": 100.0,
    "feePaid": 2.73,
    "markPoly": 0.465,
    "curEdgePP": 3.41
  },
  {
    "conditionId": "0xe284a52d608552290b056def0a62e1914b3ebe316407504f56f6361fafc68358",
    "slug": "will-bitcoin-reach-70k-in-july-2026",
    "market": "erreicht $70,000 bis 2026-08-01",
    "family": "touch",
    "side": "NO",
    "status": "OPEN",
    "entryTs": "2026-07-04T15:01:42Z",
    "entryPoly": 0.255,
    "entryFair": 0.2252,
    "entryEdgePP": -4.77,
    "shares": 134.23,
    "stakeUSD": 100.0,
    "feePaid": 1.79,
    "markPoly": 0.185,
    "curEdgePP": -3.62
  },
  {
    "conditionId": "0x1f2bc9a363013dcf06f383b73aa8c78e05e477281d8baf9c189f0e7ba8e1ccda",
    "slug": "bitcoin-above-62k-on-july-9-2026",
    "market": "über $62,000 · 2026-07-09",
    "family": "above",
    "side": "NO",
    "status": "CLOSED",
    "entryTs": "2026-07-04T15:01:42Z",
    "entryPoly": 0.61,
    "entryFair": 0.5906,
    "entryEdgePP": -4.67,
    "shares": 256.41,
    "stakeUSD": 100.0,
    "feePaid": 5.32,
    "markPoly": 0.62,
    "curEdgePP": -0.84,
    "exitTs": "2026-07-05T14:03:06Z",
    "exitMark": 0.63,
    "exitReason": "converged",
    "realizedPnl": -10.45,
    "roiPct": -10.4
  },
  {
    "conditionId": "0x5e2aecc3ca41986f8e5f1a67c4d8f5bed56c10191dd5ea0c4980e66a3d61d680",
    "slug": "will-bitcoin-dip-to-50k-in-july-2026",
    "market": "dip $50,000 bis 2026-08-01",
    "family": "touch",
    "side": "YES",
    "status": "OPEN",
    "entryTs": "2026-07-04T15:01:42Z",
    "entryPoly": 0.075,
    "entryFair": 0.1262,
    "entryEdgePP": 4.59,
    "shares": 1333.33,
    "stakeUSD": 100.0,
    "feePaid": 0.53,
    "markPoly": 0.085,
    "curEdgePP": 5.73
  },
  {
    "conditionId": "0xc9c9790c8f26dd9c8cabae9dd76be37aa86a6ded7de660e1da9d19324cf618d4",
    "slug": "will-bitcoin-reach-65k-in-july-2026",
    "market": "erreicht $65,000 bis 2026-08-01",
    "family": "touch",
    "side": "NO",
    "status": "OPEN",
    "entryTs": "2026-07-04T15:01:42Z",
    "entryPoly": 0.725,
    "entryFair": 0.6996,
    "entryEdgePP": -4.46,
    "shares": 363.64,
    "stakeUSD": 100.0,
    "feePaid": 1.93,
    "markPoly": 0.615,
    "curEdgePP": -6.28
  },
  {
    "conditionId": "0x43f1404d5230f1b925f3a7a5bd779c11ecccf9105aff9b22c337b83630c33417",
    "slug": "bitcoin-above-62k-on-july-7-2026",
    "market": "über $62,000 · 2026-07-07",
    "family": "above",
    "side": "NO",
    "status": "CLOSED",
    "entryTs": "2026-07-04T15:01:42Z",
    "entryPoly": 0.65,
    "entryFair": 0.631,
    "entryEdgePP": -4.35,
    "shares": 285.71,
    "stakeUSD": 100.0,
    "feePaid": 4.87,
    "markPoly": 0.705,
    "curEdgePP": -4.9,
    "exitTs": "2026-07-05T11:10:33Z",
    "exitMark": 0.655,
    "exitReason": "converged",
    "realizedPnl": -6.3,
    "roiPct": -6.3
  },
  {
    "conditionId": "0xcfc8e92294639f501184506ed3872081299ff9fd615754cd1ce39734d2d06351",
    "slug": "bitcoin-above-60k-on-july-8-2026",
    "market": "über $60,000 · 2026-07-08",
    "family": "above",
    "side": "NO",
    "status": "CLOSED",
    "entryTs": "2026-07-04T15:01:42Z",
    "entryPoly": 0.885,
    "entryFair": 0.8505,
    "entryEdgePP": -4.25,
    "shares": 869.57,
    "stakeUSD": 100.0,
    "feePaid": 1.64,
    "markPoly": 0.905,
    "curEdgePP": -5.45,
    "exitTs": "2026-07-05T11:10:33Z",
    "exitMark": 0.88,
    "exitReason": "converged",
    "realizedPnl": 2.71,
    "roiPct": 2.7
  },
  {
    "conditionId": "0x6811c0d6494cbe7a45cf1bde494add4e82a12e222715b71caef01c112865f120",
    "slug": "bitcoin-above-64k-on-july-6-2026",
    "market": "über $64,000 · 2026-07-06",
    "family": "above",
    "side": "NO",
    "status": "CLOSED",
    "entryTs": "2026-07-04T15:01:42Z",
    "entryPoly": 0.1805,
    "entryFair": 0.1508,
    "entryEdgePP": -4.23,
    "shares": 122.03,
    "stakeUSD": 100.0,
    "feePaid": 2.75,
    "markPoly": 0.1865,
    "curEdgePP": -3.74,
    "exitTs": "2026-07-05T08:03:35Z",
    "exitMark": 0.2125,
    "exitReason": "converged",
    "realizedPnl": -6.65,
    "roiPct": -6.7
  },
  {
    "conditionId": "0x2310ab1f44e67168b38e108de221ce7c2e2a2d93a8ab269add0382f9ceb3a037",
    "slug": "bitcoin-above-62k-on-july-8-2026",
    "market": "über $62,000 · 2026-07-08",
    "family": "above",
    "side": "NO",
    "status": "CLOSED",
    "entryTs": "2026-07-04T15:01:42Z",
    "entryPoly": 0.62,
    "entryFair": 0.6064,
    "entryEdgePP": -4.02,
    "shares": 263.16,
    "stakeUSD": 100.0,
    "feePaid": 5.11,
    "markPoly": 0.63,
    "curEdgePP": -0.58,
    "exitTs": "2026-07-05T14:03:06Z",
    "exitMark": 0.65,
    "exitReason": "converged",
    "realizedPnl": -13.0,
    "roiPct": -13.0
  },
  {
    "conditionId": "0x63eaf41ce1f475323e2202d7dfa3b1def8b82cd166f7007c50bfbf47615c7b01",
    "slug": "will-bitcoin-reach-110000-by-december-31-2026-658-339-969",
    "market": "erreicht $110,000 bis 2027-01-01",
    "family": "touch",
    "side": "NO",
    "status": "OPEN",
    "entryTs": "2026-07-04T15:01:42Z",
    "entryPoly": 0.075,
    "entryFair": 0.0409,
    "entryEdgePP": -3.94,
    "shares": 108.11,
    "stakeUSD": 100.0,
    "feePaid": 0.52,
    "markPoly": 0.075,
    "curEdgePP": -4.17
  },
  {
    "conditionId": "0x0c27b49f0c9ce6d1c48bf2c38af75e06bd9bf1575e573094df739d8c668a329f",
    "slug": "bitcoin-above-60k-on-july-9-2026",
    "market": "über $60,000 · 2026-07-09",
    "family": "above",
    "side": "NO",
    "status": "CLOSED",
    "entryTs": "2026-07-04T15:01:42Z",
    "entryPoly": 0.845,
    "entryFair": 0.8167,
    "entryEdgePP": -3.92,
    "shares": 645.16,
    "stakeUSD": 100.0,
    "feePaid": 2.11,
    "markPoly": 0.875,
    "curEdgePP": -5.63,
    "exitTs": "2026-07-05T11:10:33Z",
    "exitMark": 0.855,
    "exitReason": "converged",
    "realizedPnl": -8.56,
    "roiPct": -8.6
  },
  {
    "conditionId": "0x1dd418657a0dda226b252951f04324ed121c9537e89ab8ea1a0eb502ea424369",
    "slug": "bitcoin-above-60k-on-july-10-2026",
    "market": "über $60,000 · 2026-07-10",
    "family": "above",
    "side": "NO",
    "status": "CLOSED",
    "entryTs": "2026-07-04T15:01:42Z",
    "entryPoly": 0.815,
    "entryFair": 0.7909,
    "entryEdgePP": -3.71,
    "shares": 540.54,
    "stakeUSD": 100.0,
    "feePaid": 2.53,
    "markPoly": 0.85,
    "curEdgePP": -6.25,
    "exitTs": "2026-07-05T11:10:33Z",
    "exitMark": 0.825,
    "exitReason": "converged",
    "realizedPnl": -7.94,
    "roiPct": -7.9
  },
  {
    "conditionId": "0xf9b6b5c3c6e07afe4aad6ed9ce4fa7545f9c2baa9f1dc632cd81a085c99acfe4",
    "slug": "will-bitcoin-reach-120000-by-december-31-2026-625-425-562",
    "market": "erreicht $120,000 bis 2027-01-01",
    "family": "touch",
    "side": "NO",
    "status": "OPEN",
    "entryTs": "2026-07-04T15:01:42Z",
    "entryPoly": 0.055,
    "entryFair": 0.0223,
    "entryEdgePP": -3.66,
    "shares": 105.82,
    "stakeUSD": 100.0,
    "feePaid": 0.39,
    "markPoly": 0.045,
    "curEdgePP": -2.58
  },
  {
    "conditionId": "0x357ef67b1d8665d64339f06f3b5c250aeb6294caf708f90cfc60a51f473c8f48",
    "slug": "bitcoin-above-64k-on-july-5-2026",
    "market": "über $64,000 · 2026-07-05",
    "family": "above",
    "side": "YES",
    "status": "CLOSED",
    "entryTs": "2026-07-04T15:01:42Z",
    "entryPoly": 0.0535,
    "entryFair": 0.0931,
    "entryEdgePP": 3.59,
    "shares": 1869.16,
    "stakeUSD": 100.0,
    "feePaid": 1.61,
    "markPoly": 0.0865,
    "curEdgePP": 2.91,
    "exitTs": "2026-07-04T18:06:11Z",
    "exitMark": 0.1775,
    "exitReason": "converged",
    "realizedPnl": 230.17,
    "roiPct": 230.2
  },
  {
    "conditionId": "0xbfefe500c3fea4d8067f39246e4d9404a6fe0ea3040e1366d4ac02367d751c46",
    "slug": "will-bitcoin-dip-to-55k-in-july-2026",
    "market": "dip $55,000 bis 2026-08-01",
    "family": "touch",
    "side": "YES",
    "status": "OPEN",
    "entryTs": "2026-07-04T15:01:42Z",
    "entryPoly": 0.255,
    "entryFair": 0.3078,
    "entryEdgePP": 3.5,
    "shares": 392.16,
    "stakeUSD": 100.0,
    "feePaid": 1.79,
    "markPoly": 0.275,
    "curEdgePP": 6.49
  },
  {
    "conditionId": "0x005c612e25e7e23377f9dd3c19474fe3c186c9fa8ee93fa5bd47072c8ad95792",
    "slug": "bitcoin-above-64k-on-july-9-2026",
    "market": "über $64,000 · 2026-07-09",
    "family": "above",
    "side": "NO",
    "status": "OPEN",
    "entryTs": "2026-07-04T15:01:42Z",
    "entryPoly": 0.305,
    "entryFair": 0.2914,
    "entryEdgePP": -3.5,
    "shares": 143.88,
    "stakeUSD": 100.0,
    "feePaid": 2.13,
    "markPoly": 0.165,
    "curEdgePP": -3.76
  },
  {
    "conditionId": "0x2f30cdd3b4965f7ad0fea665384008615ec5b4ff042fe88d9bdd1ce1eb53961b",
    "slug": "bitcoin-above-58k-on-july-10-2026",
    "market": "über $58,000 · 2026-07-10",
    "family": "above",
    "side": "NO",
    "status": "OPEN",
    "entryTs": "2026-07-04T15:01:42Z",
    "entryPoly": 0.935,
    "entryFair": 0.9048,
    "entryEdgePP": -3.47,
    "shares": 1538.46,
    "stakeUSD": 100.0,
    "feePaid": 0.45,
    "markPoly": 0.921,
    "curEdgePP": -1.09
  },
  {
    "conditionId": "0x885a6abefad122348b4fbd503473d7fd1f9035d0438cf988a7591620f316a859",
    "slug": "will-bitcoin-reach-130000-by-december-31-2026-756-151-855",
    "market": "erreicht $130,000 bis 2027-01-01",
    "family": "touch",
    "side": "NO",
    "status": "OPEN",
    "entryTs": "2026-07-04T15:01:42Z",
    "entryPoly": 0.045,
    "entryFair": 0.014,
    "entryEdgePP": -3.42,
    "shares": 104.71,
    "stakeUSD": 100.0,
    "feePaid": 0.32,
    "markPoly": 0.036,
    "curEdgePP": -2.51
  },
  {
    "conditionId": "0x38903ef70b7d9ee41ea22ef2aec6287e4e6c77ec8702ca741e37d5c5df090a4d",
    "slug": "will-bitcoin-reach-72pt5k-in-july-2026",
    "market": "erreicht $72,500 bis 2026-08-01",
    "family": "touch",
    "side": "NO",
    "status": "OPEN",
    "entryTs": "2026-07-04T15:01:42Z",
    "entryPoly": 0.135,
    "entryFair": 0.1111,
    "entryEdgePP": -3.34,
    "shares": 115.61,
    "stakeUSD": 100.0,
    "feePaid": 0.95,
    "markPoly": 0.095,
    "curEdgePP": -2.21
  },
  {
    "conditionId": "0x293a934d1f8d6fd347d26584738567ebc98edf6ebc82390572c677f2b07694cc",
    "slug": "bitcoin-above-58k-on-july-9-2026",
    "market": "über $58,000 · 2026-07-09",
    "family": "above",
    "side": "NO",
    "status": "CLOSED",
    "entryTs": "2026-07-04T15:01:42Z",
    "entryPoly": 0.955,
    "entryFair": 0.9249,
    "entryEdgePP": -3.33,
    "shares": 2222.22,
    "stakeUSD": 100.0,
    "feePaid": 0.65,
    "markPoly": 0.956,
    "curEdgePP": -3.73,
    "exitTs": "2026-07-05T11:10:33Z",
    "exitMark": 0.953,
    "exitReason": "converged",
    "realizedPnl": 3.79,
    "roiPct": 3.8
  },
  {
    "conditionId": "0x7d427ddb413ca92722f24cc28ed53a3eb6100e3c309405cd4e44165bb0acfe00",
    "slug": "bitcoin-above-64k-on-july-10-2026",
    "market": "über $64,000 · 2026-07-10",
    "family": "above",
    "side": "NO",
    "status": "OPEN",
    "entryTs": "2026-07-04T15:01:42Z",
    "entryPoly": 0.32,
    "entryFair": 0.3107,
    "entryEdgePP": -3.17,
    "shares": 147.06,
    "stakeUSD": 100.0,
    "feePaid": 2.24,
    "markPoly": 0.205,
    "curEdgePP": -4.44
  },
  {
    "conditionId": "0xcf90979c656e437059e2651187f9eaceabb821d4519429b72a69a068090a8bf5",
    "slug": "bitcoin-above-64k-on-july-8-2026",
    "market": "über $64,000 · 2026-07-08",
    "family": "above",
    "side": "NO",
    "status": "OPEN",
    "entryTs": "2026-07-04T15:01:42Z",
    "entryPoly": 0.275,
    "entryFair": 0.2643,
    "entryEdgePP": -3.0,
    "shares": 137.93,
    "stakeUSD": 100.0,
    "feePaid": 1.93,
    "markPoly": 0.135,
    "curEdgePP": -5.46
  },
  {
    "conditionId": "0xf0a4c0bc8a8162f0ac95b5a5af7fa665d20a19ca0db03b9117514dafc695f15e",
    "slug": "will-bitcoin-reach-140000-by-december-31-2026-131-829-299",
    "market": "erreicht $140,000 bis 2027-01-01",
    "family": "touch",
    "side": "NO",
    "status": "OPEN",
    "entryTs": "2026-07-04T15:01:42Z",
    "entryPoly": 0.035,
    "entryFair": 0.0103,
    "entryEdgePP": -2.72,
    "shares": 103.63,
    "stakeUSD": 100.0,
    "feePaid": 0.25,
    "markPoly": 0.035,
    "curEdgePP": -2.74
  },
  {
    "conditionId": "0xd5a422e44c9b421ca08dcfd3d3cb6275648b4cbc69eb8f8ad7e2c70e6edd7c70",
    "slug": "bitcoin-above-60k-on-july-7-2026",
    "market": "über $60,000 · 2026-07-07",
    "family": "above",
    "side": "NO",
    "status": "CLOSED",
    "entryTs": "2026-07-04T15:01:42Z",
    "entryPoly": 0.91,
    "entryFair": 0.8892,
    "entryEdgePP": -2.71,
    "shares": 1111.11,
    "stakeUSD": 100.0,
    "feePaid": 1.29,
    "markPoly": 0.935,
    "curEdgePP": -6.17,
    "exitTs": "2026-07-05T11:10:33Z",
    "exitMark": 0.905,
    "exitReason": "converged",
    "realizedPnl": 4.27,
    "roiPct": 4.3
  },
  {
    "conditionId": "0xdfbe36a1200c4ec361aa20733ede4d33085eef400c11d28a00079a2ba46d3d05",
    "slug": "will-bitcoin-dip-to-47pt5k-in-july-2026",
    "market": "dip $47,500 bis 2026-08-01",
    "family": "touch",
    "side": "YES",
    "status": "OPEN",
    "entryTs": "2026-07-04T15:01:42Z",
    "entryPoly": 0.045,
    "entryFair": 0.0744,
    "entryEdgePP": 2.62,
    "shares": 2222.22,
    "stakeUSD": 100.0,
    "feePaid": 0.32,
    "markPoly": 0.045,
    "curEdgePP": 4.05
  },
  {
    "conditionId": "0xa7b594ae07d5c1590fa86028fcc2f8705990437237416556c05837a08b2e1cda",
    "slug": "will-bitcoin-reach-150000-by-december-31-2026-557-246-971",
    "market": "erreicht $150,000 bis 2027-01-01",
    "family": "touch",
    "side": "NO",
    "status": "OPEN",
    "entryTs": "2026-07-04T15:01:42Z",
    "entryPoly": 0.032,
    "entryFair": 0.0083,
    "entryEdgePP": -2.59,
    "shares": 103.31,
    "stakeUSD": 100.0,
    "feePaid": 0.22,
    "markPoly": 0.031,
    "curEdgePP": -2.58
  },
  {
    "conditionId": "0x6e7647e8f1e27cca3e0154146dfe503d2c4b4facb4439e25d4c30c3db5d0da1d",
    "slug": "bitcoin-above-66k-on-july-10-2026",
    "market": "über $66,000 · 2026-07-10",
    "family": "above",
    "side": "NO",
    "status": "OPEN",
    "entryTs": "2026-07-04T15:01:42Z",
    "entryPoly": 0.13,
    "entryFair": 0.1139,
    "entryEdgePP": -2.52,
    "shares": 114.94,
    "stakeUSD": 100.0,
    "feePaid": 0.91,
    "markPoly": 0.055,
    "curEdgePP": -2.97
  },
  {
    "conditionId": "0x28f59e8824137912266b5c8c6960ca458af9b963a5468ac6bc2d6ff05483bb91",
    "slug": "bitcoin-above-62k-on-july-6-2026",
    "market": "über $62,000 · 2026-07-06",
    "family": "above",
    "side": "YES",
    "status": "CLOSED",
    "entryTs": "2026-07-04T15:11:16Z",
    "entryPoly": 0.685,
    "entryFair": 0.7482,
    "entryEdgePP": 4.12,
    "shares": 145.99,
    "stakeUSD": 100.0,
    "feePaid": 3.99,
    "exitTs": "2026-07-04T15:52:02Z",
    "exitMark": 0.745,
    "exitReason": "converged",
    "realizedPnl": 4.77,
    "roiPct": 4.8
  },
  {
    "conditionId": "0xf43c98fc3069d7cd2ec2f1825c4e1285c6870d0cdf4989061930d8cc4555a03a",
    "slug": "bitcoin-above-62k-on-july-5-2026",
    "market": "über $62,000 · 2026-07-05",
    "family": "above",
    "side": "YES",
    "status": "CLOSED",
    "entryTs": "2026-07-04T15:11:16Z",
    "entryPoly": 0.835,
    "entryFair": 0.8847,
    "entryEdgePP": 3.81,
    "shares": 119.76,
    "stakeUSD": 100.0,
    "feePaid": 1.9,
    "exitTs": "2026-07-04T15:52:02Z",
    "exitMark": 0.895,
    "exitReason": "thesis_break",
    "realizedPnl": 5.29,
    "roiPct": 5.3
  },
  {
    "conditionId": "0x578327f87338039e1545315a124e3ace202fb8fa6bfbab58dba26616bdc1d47f",
    "slug": "bitcoin-above-60k-on-july-6-2026",
    "market": "über $60,000 · 2026-07-06",
    "family": "above",
    "side": "YES",
    "status": "CLOSED",
    "entryTs": "2026-07-04T15:11:16Z",
    "entryPoly": 0.945,
    "entryFair": 0.9768,
    "entryEdgePP": 2.79,
    "shares": 105.82,
    "stakeUSD": 100.0,
    "feePaid": 0.62,
    "exitTs": "2026-07-04T15:52:02Z",
    "exitMark": 0.9665,
    "exitReason": "converged",
    "realizedPnl": 1.66,
    "roiPct": 1.7
  },
  {
    "conditionId": "0xf43c98fc3069d7cd2ec2f1825c4e1285c6870d0cdf4989061930d8cc4555a03a",
    "slug": "bitcoin-above-62k-on-july-5-2026",
    "market": "über $62,000 · 2026-07-05",
    "family": "above",
    "side": "NO",
    "status": "CLOSED",
    "entryTs": "2026-07-04T15:52:02Z",
    "entryPoly": 0.895,
    "entryFair": 0.8553,
    "entryEdgePP": -4.71,
    "shares": 952.38,
    "stakeUSD": 100.0,
    "feePaid": 0.82,
    "markPoly": 0.947,
    "curEdgePP": -2.61,
    "exitTs": "2026-07-05T14:03:06Z",
    "exitMark": 0.9875,
    "exitReason": "converged",
    "realizedPnl": -88.92,
    "roiPct": -88.9
  },
  {
    "conditionId": "0xa4fc5376f2975730fc560c9c3008f434112f2c2918c79b3712287b4f3fe2cd06",
    "slug": "bitcoin-above-64k-on-july-7-2026",
    "market": "über $64,000 · 2026-07-07",
    "family": "above",
    "side": "NO",
    "status": "OPEN",
    "entryTs": "2026-07-04T15:52:02Z",
    "entryPoly": 0.285,
    "entryFair": 0.2615,
    "entryEdgePP": -4.34,
    "shares": 139.86,
    "stakeUSD": 100.0,
    "feePaid": 1.99,
    "markPoly": 0.085,
    "curEdgePP": -4.69
  },
  {
    "conditionId": "0x14a8ace91c53e7212803d2a3161363562638067746a3850b69389336c44816b0",
    "slug": "bitcoin-above-58k-on-july-11-2026",
    "market": "über $58,000 · 2026-07-11",
    "family": "above",
    "side": "NO",
    "status": "CLOSED",
    "entryTs": "2026-07-04T16:33:44Z",
    "entryPoly": 0.95,
    "entryFair": 0.8964,
    "entryEdgePP": -5.71,
    "shares": 2000.0,
    "stakeUSD": 100.0,
    "feePaid": 0.83,
    "wasNew": true,
    "markPoly": 0.935,
    "curEdgePP": -5.29,
    "exitTs": "2026-07-05T11:10:33Z",
    "exitMark": 0.932,
    "exitReason": "converged",
    "realizedPnl": 35.17,
    "roiPct": 35.2
  },
  {
    "conditionId": "0x859ebed183e0e4d01e16ef7c5da8b4655e052de53e03e2895785a7370bdb2d83",
    "slug": "bitcoin-above-60k-on-july-11-2026",
    "market": "über $60,000 · 2026-07-11",
    "family": "above",
    "side": "NO",
    "status": "CLOSED",
    "entryTs": "2026-07-04T16:33:44Z",
    "entryPoly": 0.825,
    "entryFair": 0.7853,
    "entryEdgePP": -5.2,
    "shares": 571.43,
    "stakeUSD": 100.0,
    "feePaid": 2.53,
    "wasNew": true,
    "markPoly": 0.83,
    "curEdgePP": -5.83,
    "exitTs": "2026-07-05T11:10:33Z",
    "exitMark": 0.815,
    "exitReason": "converged",
    "realizedPnl": 3.18,
    "roiPct": 3.2
  },
  {
    "conditionId": "0x1578c0c4a0a5c3c8f5844b16a0f284cdb774e5b737155b834765d6730764e768",
    "slug": "bitcoin-above-62k-on-july-11-2026",
    "market": "über $62,000 · 2026-07-11",
    "family": "above",
    "side": "NO",
    "status": "CLOSED",
    "entryTs": "2026-07-04T16:33:44Z",
    "entryPoly": 0.605,
    "entryFair": 0.5962,
    "entryEdgePP": -3.65,
    "shares": 253.16,
    "stakeUSD": 100.0,
    "feePaid": 5.57,
    "wasNew": true,
    "markPoly": 0.635,
    "curEdgePP": -5.54,
    "exitTs": "2026-07-05T11:10:33Z",
    "exitMark": 0.6,
    "exitReason": "converged",
    "realizedPnl": -4.3,
    "roiPct": -4.3
  },
  {
    "conditionId": "0xb2b222cf79fcf899e479bbf711e02198af67817a2740286f71b950830717e3e2",
    "slug": "bitcoin-above-64k-on-july-11-2026",
    "market": "über $64,000 · 2026-07-11",
    "family": "above",
    "side": "NO",
    "status": "CLOSED",
    "entryTs": "2026-07-04T18:06:11Z",
    "entryPoly": 0.4,
    "entryFair": 0.389,
    "entryEdgePP": -3.9,
    "shares": 166.67,
    "stakeUSD": 100.0,
    "feePaid": 5.18,
    "wasNew": true,
    "markPoly": 0.38,
    "curEdgePP": -4.57,
    "exitTs": "2026-07-05T11:10:33Z",
    "exitMark": 0.34,
    "exitReason": "converged",
    "realizedPnl": 4.82,
    "roiPct": 4.8
  },
  {
    "conditionId": "0x9963ed8f0f3a5d6677c7dc2e4179cded497227958facac11653111334ca82ab1",
    "slug": "bitcoin-above-66k-on-july-9-2026",
    "market": "über $66,000 · 2026-07-09",
    "family": "above",
    "side": "NO",
    "status": "OPEN",
    "entryTs": "2026-07-04T18:06:11Z",
    "entryPoly": 0.145,
    "entryFair": 0.1249,
    "entryEdgePP": -3.02,
    "shares": 116.96,
    "stakeUSD": 100.0,
    "feePaid": 1.02,
    "wasNew": false,
    "markPoly": 0.045,
    "curEdgePP": -2.69
  },
  {
    "conditionId": "0x024b68f77bfc019341ee3db8f57c103334e4b9430bba4746d8c94aafd8b36fee",
    "slug": "will-bitcoin-dip-to-45000-by-december-31-2026-674-923-755-971-998-525-926-245-316-517-544-589-965-923-986-841-815-224-586-231-289-533",
    "market": "dip $45,000 bis 2027-01-01",
    "family": "touch",
    "side": "YES",
    "status": "OPEN",
    "entryTs": "2026-07-04T18:06:11Z",
    "entryPoly": 0.355,
    "entryFair": 0.4077,
    "entryEdgePP": 2.78,
    "shares": 281.69,
    "stakeUSD": 100.0,
    "feePaid": 2.48,
    "wasNew": false,
    "markPoly": 0.365,
    "curEdgePP": 4.79
  },
  {
    "conditionId": "0xce3c54c3e773e8b3bf73e4c12af93205b21195d03b9c386e22f274b9acfc2c56",
    "slug": "will-bitcoin-dip-to-50000-by-december-31-2026-454-325-222-878-949-487-451-853-523",
    "market": "dip $50,000 bis 2027-01-01",
    "family": "touch",
    "side": "YES",
    "status": "CLOSED",
    "tokenId": "13887983551129862992605123088744175927084435631400400451585519366058907542147",
    "entryTs": "2026-07-05T08:03:35Z",
    "entryPoly": 0.505,
    "entryFair": 0.5495,
    "entryEdgePP": 0.99,
    "shares": 198.02,
    "stakeUSD": 100.0,
    "realShares": 9.901,
    "feePaid": 6.92,
    "wasNew": false,
    "markPoly": 0.505,
    "curEdgePP": 1.71,
    "exitTs": "2026-07-05T23:13:36Z",
    "exitMark": 0.505,
    "exitReason": "converged",
    "realizedPnl": -6.92,
    "roiPct": -6.9
  },
  {
    "conditionId": "0x1578c0c4a0a5c3c8f5844b16a0f284cdb774e5b737155b834765d6730764e768",
    "slug": "bitcoin-above-62k-on-july-11-2026",
    "market": "über $62,000 · 2026-07-11",
    "family": "above",
    "side": "YES",
    "status": "CLOSED",
    "tokenId": "84274189461117753774320113636014257451981580626850548700734188421030864056438",
    "entryTs": "2026-07-05T11:10:33Z",
    "entryPoly": 0.6,
    "entryFair": 0.6514,
    "entryEdgePP": 2.34,
    "shares": 166.67,
    "stakeUSD": 100.0,
    "realShares": 8.3333,
    "feePaid": 6.26,
    "wasNew": true,
    "markPoly": 0.655,
    "curEdgePP": 1.33,
    "exitTs": "2026-07-06T13:59:25Z",
    "exitMark": 0.505,
    "exitReason": "converged",
    "realizedPnl": -22.09,
    "roiPct": -22.1
  },
  {
    "conditionId": "0x6811c0d6494cbe7a45cf1bde494add4e82a12e222715b71caef01c112865f120",
    "slug": "bitcoin-above-64k-on-july-6-2026",
    "market": "über $64,000 · 2026-07-06",
    "family": "above",
    "side": "NO",
    "status": "CLOSED",
    "tokenId": "30641977119228224603370169421842784079342342431133105211128739896187644855279",
    "entryTs": "2026-07-05T11:10:33Z",
    "entryPoly": 0.1535,
    "entryFair": 0.1126,
    "entryEdgePP": -5.16,
    "shares": 118.13,
    "stakeUSD": 100.0,
    "realShares": 5.9067,
    "feePaid": 1.09,
    "wasNew": false,
    "markPoly": 0.0655,
    "curEdgePP": -4.41,
    "exitTs": "2026-07-06T13:59:25Z",
    "exitMark": 0.0035,
    "exitReason": "converged",
    "realizedPnl": 16.63,
    "roiPct": 16.6
  },
  {
    "conditionId": "0x2b2aa6c11544142c0d784aa50309722ad4002166973bf6e4122a4a8e84743034",
    "slug": "bitcoin-above-66k-on-july-7-2026",
    "market": "über $66,000 · 2026-07-07",
    "family": "above",
    "side": "NO",
    "status": "CLOSED",
    "tokenId": "75495577040724968433667489946125773528397843015206118979804775192186513792823",
    "entryTs": "2026-07-05T11:10:33Z",
    "entryPoly": 0.0465,
    "entryFair": 0.0139,
    "entryEdgePP": -3.59,
    "shares": 104.88,
    "stakeUSD": 100.0,
    "realShares": 5.2438,
    "feePaid": 0.39,
    "wasNew": false,
    "markPoly": 0.0205,
    "curEdgePP": -1.01,
    "exitTs": "2026-07-06T13:59:25Z",
    "exitMark": 0.0085,
    "exitReason": "converged",
    "realizedPnl": 3.6,
    "roiPct": 3.6
  },
  {
    "conditionId": "0x43f1404d5230f1b925f3a7a5bd779c11ecccf9105aff9b22c337b83630c33417",
    "slug": "bitcoin-above-62k-on-july-7-2026",
    "market": "über $62,000 · 2026-07-07",
    "family": "above",
    "side": "YES",
    "status": "CLOSED",
    "tokenId": "1233424804878739626680538643861947895049546312488684818171809341210685481681",
    "entryTs": "2026-07-05T11:10:33Z",
    "entryPoly": 0.655,
    "entryFair": 0.6874,
    "entryEdgePP": 0.83,
    "shares": 152.67,
    "stakeUSD": 100.0,
    "realShares": 7.6336,
    "feePaid": 4.62,
    "wasNew": false,
    "markPoly": 0.675,
    "curEdgePP": 1.0,
    "exitTs": "2026-07-05T15:24:27Z",
    "exitMark": 0.685,
    "exitReason": "converged",
    "realizedPnl": -0.04,
    "roiPct": -0.0
  },
  {
    "conditionId": "0x2771c61f82c2dacf5996c4242860d3331b5f644541325b6de3a92549912b6ad7",
    "slug": "bitcoin-above-66k-on-july-8-2026",
    "market": "über $66,000 · 2026-07-08",
    "family": "above",
    "side": "NO",
    "status": "OPEN",
    "tokenId": "104057531887542386656679920886048295971392254967385392835237966857207119791432",
    "entryTs": "2026-07-05T11:10:33Z",
    "entryPoly": 0.0725,
    "entryFair": 0.0433,
    "entryEdgePP": -3.43,
    "shares": 107.82,
    "stakeUSD": 100.0,
    "realShares": 5.3908,
    "feePaid": 0.51,
    "wasNew": false,
    "markPoly": 0.015,
    "curEdgePP": -0.85
  },
  {
    "conditionId": "0xec540d631a88397ca01a17e48193019b4d680fde10087a38d5c8467bfaae18c0",
    "slug": "will-bitcoin-dip-to-45k-in-july-2026",
    "market": "dip $45,000 bis 2026-08-01",
    "family": "touch",
    "side": "YES",
    "status": "OPEN",
    "tokenId": "5421398228940954401467007478148592154055068315416135326259909253093921651338",
    "entryTs": "2026-07-05T11:10:33Z",
    "entryPoly": 0.0285,
    "entryFair": 0.0556,
    "entryEdgePP": 2.51,
    "shares": 3508.77,
    "stakeUSD": 100.0,
    "realShares": 175.4386,
    "feePaid": 0.2,
    "wasNew": false,
    "markPoly": 0.0225,
    "curEdgePP": 3.54
  },
  {
    "conditionId": "0x859ebed183e0e4d01e16ef7c5da8b4655e052de53e03e2895785a7370bdb2d83",
    "slug": "bitcoin-above-60k-on-july-11-2026",
    "market": "über $60,000 · 2026-07-11",
    "family": "above",
    "side": "YES",
    "status": "OPEN",
    "tokenId": "59626010928585859869941679751867054552447385575030481090464284491298441044604",
    "entryTs": "2026-07-05T14:03:06Z",
    "entryPoly": 0.82,
    "entryFair": 0.8588,
    "entryEdgePP": 2.62,
    "shares": 121.95,
    "stakeUSD": 100.0,
    "realShares": 6.0976,
    "feePaid": 1.26,
    "wasNew": true,
    "markPoly": 0.77,
    "curEdgePP": 1.44
  },
  {
    "conditionId": "0xded99cb4e5d4dcd0bb4de21c852a3985d5dc0c8ab5d78f4716ee9f4066ce28fc",
    "slug": "bitcoin-above-68k-on-july-10-2026",
    "market": "über $68,000 · 2026-07-10",
    "family": "above",
    "side": "NO",
    "status": "OPEN",
    "tokenId": "97516241183584776502022201318087409418909363194420934051869159837722891181305",
    "entryTs": "2026-07-05T15:24:27Z",
    "entryPoly": 0.0405,
    "entryFair": 0.0145,
    "entryEdgePP": -2.88,
    "shares": 104.22,
    "stakeUSD": 100.0,
    "realShares": 5.211,
    "feePaid": 0.28,
    "wasNew": true,
    "markPoly": 0.022,
    "curEdgePP": -1.73
  },
  {
    "conditionId": "0x7b9072e6a9cdcf022c4f098564e8ee612d544e179e4a33dcc2790fbaa778daa8",
    "slug": "will-bitcoin-reach-70000-by-december-31-2026-from-june-8",
    "market": "erreicht $70,000 bis 2027-01-01",
    "family": "touch",
    "side": "NO",
    "status": "CLOSED",
    "tokenId": "107869950127184141743772429738701578723770582686430100389837827512148691029625",
    "entryTs": "2026-07-05T17:24:34Z",
    "entryPoly": 0.7,
    "entryFair": 0.6614,
    "entryEdgePP": -5.96,
    "shares": 333.33,
    "stakeUSD": 100.0,
    "realShares": 16.6667,
    "feePaid": 4.24,
    "wasNew": false,
    "markPoly": 0.69,
    "curEdgePP": -4.87,
    "exitTs": "2026-07-05T23:13:36Z",
    "exitMark": 0.695,
    "exitReason": "converged",
    "realizedPnl": -2.57,
    "roiPct": -2.6
  },
  {
    "conditionId": "0x14a8ace91c53e7212803d2a3161363562638067746a3850b69389336c44816b0",
    "slug": "bitcoin-above-58k-on-july-11-2026",
    "market": "über $58,000 · 2026-07-11",
    "family": "above",
    "side": "YES",
    "status": "OPEN",
    "tokenId": "235228375068988311784373467098778267697933550045290388660344509097256131722",
    "entryTs": "2026-07-05T19:40:45Z",
    "entryPoly": 0.9325,
    "entryFair": 0.9668,
    "entryEdgePP": 2.96,
    "shares": 107.24,
    "stakeUSD": 100.0,
    "realShares": 5.3619,
    "feePaid": 0.47,
    "wasNew": true,
    "markPoly": 0.9105,
    "curEdgePP": 1.61
  },
  {
    "conditionId": "0x43f1404d5230f1b925f3a7a5bd779c11ecccf9105aff9b22c337b83630c33417",
    "slug": "bitcoin-above-62k-on-july-7-2026",
    "market": "über $62,000 · 2026-07-07",
    "family": "above",
    "side": "YES",
    "status": "CLOSED",
    "tokenId": "1233424804878739626680538643861947895049546312488684818171809341210685481681",
    "entryTs": "2026-07-05T19:40:45Z",
    "entryPoly": 0.685,
    "entryFair": 0.7183,
    "entryEdgePP": 1.13,
    "shares": 145.99,
    "stakeUSD": 100.0,
    "realShares": 7.2993,
    "feePaid": 3.08,
    "wasNew": false,
    "markPoly": 0.665,
    "curEdgePP": 1.31,
    "exitTs": "2026-07-05T23:13:36Z",
    "exitMark": 0.875,
    "exitReason": "converged",
    "realizedPnl": 24.66,
    "roiPct": 24.7
  },
  {
    "conditionId": "0xb2b222cf79fcf899e479bbf711e02198af67817a2740286f71b950830717e3e2",
    "slug": "bitcoin-above-64k-on-july-11-2026",
    "market": "über $64,000 · 2026-07-11",
    "family": "above",
    "side": "YES",
    "status": "CLOSED",
    "tokenId": "107268250696899722989818361141009210381365569902222649850764832303284830201491",
    "entryTs": "2026-07-05T23:13:36Z",
    "entryPoly": 0.485,
    "entryFair": 0.5213,
    "entryEdgePP": 0.23,
    "shares": 206.19,
    "stakeUSD": 100.0,
    "realShares": 10.3093,
    "feePaid": 6.3,
    "wasNew": true,
    "exitTs": "2026-07-06T04:24:40Z",
    "exitMark": 0.415,
    "exitReason": "converged",
    "realizedPnl": -20.73,
    "roiPct": -20.7
  },
  {
    "conditionId": "0xbca0b596e44dd239eeafdda4a3621ef73d76b07d3f4752e2bf8d7229fecda288",
    "slug": "bitcoin-above-62k-on-july-12-2026",
    "market": "über $62,000 · 2026-07-12",
    "family": "above",
    "side": "YES",
    "status": "CLOSED",
    "tokenId": "101172364260676833930787157830970168089286336357650038338928077567884358953049",
    "entryTs": "2026-07-05T23:13:36Z",
    "entryPoly": 0.74,
    "entryFair": 0.7759,
    "entryEdgePP": 1.77,
    "shares": 135.14,
    "stakeUSD": 100.0,
    "realShares": 6.7568,
    "feePaid": 5.29,
    "wasNew": true,
    "markPoly": 0.635,
    "curEdgePP": 2.06,
    "exitTs": "2026-07-06T13:59:25Z",
    "exitMark": 0.505,
    "exitReason": "converged",
    "realizedPnl": -37.05,
    "roiPct": -37.0
  },
  {
    "conditionId": "0x1239389645c8a73b170b78ef3a83d69b6cf1d2711d412829ea8836660b08fc93",
    "slug": "will-bitcoin-reach-85000-by-december-31-2026-from-june-8",
    "market": "erreicht $85,000 bis 2027-01-01",
    "family": "touch",
    "side": "YES",
    "status": "CLOSED",
    "tokenId": "27201221676173593121678787264361008606480627771007041356248031697735484721466",
    "entryTs": "2026-07-05T23:13:36Z",
    "entryPoly": 0.215,
    "entryFair": 0.2609,
    "entryEdgePP": 3.08,
    "shares": 465.12,
    "stakeUSD": 100.0,
    "realShares": 23.2558,
    "feePaid": 3.02,
    "wasNew": false,
    "markPoly": 0.215,
    "curEdgePP": 0.95,
    "exitTs": "2026-07-06T13:59:25Z",
    "exitMark": 0.215,
    "exitReason": "converged",
    "realizedPnl": -3.02,
    "roiPct": -3.0
  },
  {
    "conditionId": "0x84fdc3f917e34acca874f93d978e84ed0c08969903ddf40a5d65274b3a5b4fdf",
    "slug": "will-bitcoin-reach-75000-by-december-31-2026-from-june-8",
    "market": "erreicht $75,000 bis 2027-01-01",
    "family": "touch",
    "side": "YES",
    "status": "CLOSED",
    "tokenId": "110439449768613802110790243898351375650535979513820669361590931221457616396762",
    "entryTs": "2026-07-05T23:13:36Z",
    "entryPoly": 0.485,
    "entryFair": 0.5215,
    "entryEdgePP": 0.25,
    "shares": 206.19,
    "stakeUSD": 100.0,
    "realShares": 10.3093,
    "feePaid": 6.79,
    "wasNew": false,
    "exitTs": "2026-07-06T04:24:40Z",
    "exitMark": 0.485,
    "exitReason": "converged",
    "realizedPnl": -6.79,
    "roiPct": -6.8
  },
  {
    "conditionId": "0x62ea8d365ecde2ebeb581cb7085f74115aebfc4737d37ec931e919a258ada9c3",
    "slug": "bitcoin-above-60k-on-july-12-2026",
    "market": "über $60,000 · 2026-07-12",
    "family": "above",
    "side": "YES",
    "status": "OPEN",
    "tokenId": "74549561616675482794402199721441852779935362426853543227627020444811989238946",
    "entryTs": "2026-07-06T04:24:40Z",
    "entryPoly": 0.865,
    "entryFair": 0.8957,
    "entryEdgePP": 2.12,
    "shares": 115.61,
    "stakeUSD": 100.0,
    "realShares": 5.7803,
    "feePaid": 0.95,
    "wasNew": true,
    "markPoly": 0.75,
    "curEdgePP": 1.53
  },
  {
    "conditionId": "0xce3c54c3e773e8b3bf73e4c12af93205b21195d03b9c386e22f274b9acfc2c56",
    "slug": "will-bitcoin-dip-to-50000-by-december-31-2026-454-325-222-878-949-487-451-853-523",
    "market": "dip $50,000 bis 2027-01-01",
    "family": "touch",
    "side": "NO",
    "status": "CLOSED",
    "tokenId": "41832664285845832459030640969891483663884721696292020563915305291791682631668",
    "entryTs": "2026-07-06T04:24:40Z",
    "entryPoly": 0.505,
    "entryFair": 0.5385,
    "entryEdgePP": -0.11,
    "shares": 202.02,
    "stakeUSD": 100.0,
    "realShares": 10.101,
    "feePaid": 6.71,
    "wasNew": false,
    "markPoly": 0.525,
    "curEdgePP": -0.81,
    "exitTs": "2026-07-06T13:59:25Z",
    "exitMark": 0.535,
    "exitReason": "converged",
    "realizedPnl": -12.77,
    "roiPct": -12.8
  },
  {
    "conditionId": "0x10492aaf796455be720f0fb12576f029909d3c2aad61c38811f73b15b7690fe6",
    "slug": "bitcoin-above-62k-on-july-10-2026",
    "market": "über $62,000 · 2026-07-10",
    "family": "above",
    "side": "YES",
    "status": "CLOSED",
    "tokenId": "92926264709669180674245674272589745809119428539673895391063230154803974055191",
    "entryTs": "2026-07-06T09:09:19Z",
    "entryPoly": 0.665,
    "entryFair": 0.7006,
    "entryEdgePP": 1.22,
    "shares": 150.38,
    "stakeUSD": 100.0,
    "realShares": 7.5188,
    "feePaid": 5.8,
    "wasNew": false,
    "exitTs": "2026-07-06T13:59:25Z",
    "exitMark": 0.505,
    "exitReason": "converged",
    "realizedPnl": -29.86,
    "roiPct": -29.9
  },
  {
    "conditionId": "0x2310ab1f44e67168b38e108de221ce7c2e2a2d93a8ab269add0382f9ceb3a037",
    "slug": "bitcoin-above-62k-on-july-8-2026",
    "market": "über $62,000 · 2026-07-08",
    "family": "above",
    "side": "YES",
    "status": "CLOSED",
    "tokenId": "64117549111635593560329353245069706937159526126701088188625563358425699821853",
    "entryTs": "2026-07-06T09:09:19Z",
    "entryPoly": 0.695,
    "entryFair": 0.7291,
    "entryEdgePP": 1.27,
    "shares": 143.88,
    "stakeUSD": 100.0,
    "realShares": 7.1942,
    "feePaid": 5.54,
    "wasNew": false,
    "exitTs": "2026-07-06T13:59:25Z",
    "exitMark": 0.485,
    "exitReason": "thesis_break",
    "realizedPnl": -35.75,
    "roiPct": -35.8
  },
  {
    "conditionId": "0x43f1404d5230f1b925f3a7a5bd779c11ecccf9105aff9b22c337b83630c33417",
    "slug": "bitcoin-above-62k-on-july-7-2026",
    "market": "über $62,000 · 2026-07-07",
    "family": "above",
    "side": "YES",
    "status": "CLOSED",
    "tokenId": "1233424804878739626680538643861947895049546312488684818171809341210685481681",
    "entryTs": "2026-07-06T09:09:19Z",
    "entryPoly": 0.735,
    "entryFair": 0.7665,
    "entryEdgePP": 1.29,
    "shares": 136.05,
    "stakeUSD": 100.0,
    "realShares": 6.8027,
    "feePaid": 5.33,
    "wasNew": false,
    "exitTs": "2026-07-06T13:59:25Z",
    "exitMark": 0.495,
    "exitReason": "thesis_break",
    "realizedPnl": -37.98,
    "roiPct": -38.0
  },
  {
    "conditionId": "0x1578c0c4a0a5c3c8f5844b16a0f284cdb774e5b737155b834765d6730764e768",
    "slug": "bitcoin-above-62k-on-july-11-2026",
    "market": "über $62,000 · 2026-07-11",
    "family": "above",
    "side": "YES",
    "status": "OPEN",
    "tokenId": "84274189461117753774320113636014257451981580626850548700734188421030864056438",
    "entryTs": "2026-07-06T13:59:25Z",
    "entryPoly": 0.505,
    "entryFair": 0.541,
    "entryEdgePP": 0.14,
    "shares": 198.02,
    "stakeUSD": 100.0,
    "realShares": 9.901,
    "feePaid": 3.46,
    "wasNew": true
  },
  {
    "conditionId": "0xbca0b596e44dd239eeafdda4a3621ef73d76b07d3f4752e2bf8d7229fecda288",
    "slug": "bitcoin-above-62k-on-july-12-2026",
    "market": "über $62,000 · 2026-07-12",
    "family": "above",
    "side": "NO",
    "status": "OPEN",
    "tokenId": "45634847444373181499279963116843932715169431789852457536784125994089355708831",
    "entryTs": "2026-07-06T13:59:25Z",
    "entryPoly": 0.505,
    "entryFair": 0.5393,
    "entryEdgePP": -0.03,
    "shares": 202.02,
    "stakeUSD": 100.0,
    "realShares": 10.101,
    "feePaid": 3.46,
    "wasNew": true
  },
  {
    "conditionId": "0x28f59e8824137912266b5c8c6960ca458af9b963a5468ac6bc2d6ff05483bb91",
    "slug": "bitcoin-above-62k-on-july-6-2026",
    "market": "über $62,000 · 2026-07-06",
    "family": "above",
    "side": "NO",
    "status": "OPEN",
    "tokenId": "106541599852680945229467459206120643033508169120174139981143594297487111731650",
    "entryTs": "2026-07-06T13:59:25Z",
    "entryPoly": 0.455,
    "entryFair": 0.3659,
    "entryEdgePP": -12.1,
    "shares": 183.49,
    "stakeUSD": 100.0,
    "realShares": 9.1743,
    "feePaid": 3.19,
    "wasNew": false
  },
  {
    "conditionId": "0xce3c54c3e773e8b3bf73e4c12af93205b21195d03b9c386e22f274b9acfc2c56",
    "slug": "will-bitcoin-dip-to-50000-by-december-31-2026-454-325-222-878-949-487-451-853-523",
    "market": "dip $50,000 bis 2027-01-01",
    "family": "touch",
    "side": "YES",
    "status": "OPEN",
    "tokenId": "13887983551129862992605123088744175927084435631400400451585519366058907542147",
    "entryTs": "2026-07-06T13:59:25Z",
    "entryPoly": 0.535,
    "entryFair": 0.5822,
    "entryEdgePP": 1.46,
    "shares": 186.92,
    "stakeUSD": 100.0,
    "realShares": 9.3458,
    "feePaid": 3.26,
    "wasNew": false
  },
  {
    "conditionId": "0x7b9072e6a9cdcf022c4f098564e8ee612d544e179e4a33dcc2790fbaa778daa8",
    "slug": "will-bitcoin-reach-70000-by-december-31-2026-from-june-8",
    "market": "erreicht $70,000 bis 2027-01-01",
    "family": "touch",
    "side": "NO",
    "status": "OPEN",
    "tokenId": "107869950127184141743772429738701578723770582686430100389837827512148691029625",
    "entryTs": "2026-07-06T13:59:25Z",
    "entryPoly": 0.67,
    "entryFair": 0.6244,
    "entryEdgePP": -6.87,
    "shares": 303.03,
    "stakeUSD": 100.0,
    "realShares": 15.1515,
    "feePaid": 2.31,
    "wasNew": false
  },
  {
    "conditionId": "0xbb379a14cd03f68c35c279ddbd928a6326f4fd2e21827f8cdaaf59715d6df50e",
    "slug": "will-bitcoin-reach-90000-by-december-31-2026-113-862-581-343",
    "market": "erreicht $90,000 bis 2027-01-01",
    "family": "touch",
    "side": "NO",
    "status": "OPEN",
    "tokenId": "89935193776001764234914810530894985625350942201527563326613427606200761992090",
    "entryTs": "2026-07-06T13:59:25Z",
    "entryPoly": 0.185,
    "entryFair": 0.1513,
    "entryEdgePP": -4.67,
    "shares": 122.7,
    "stakeUSD": 100.0,
    "realShares": 6.135,
    "feePaid": 1.3,
    "wasNew": false
  },
  {
    "conditionId": "0xda77b0cbaae44916e756e4e9c216d082e5c1ca12d92294a2fa9ee963be3303c8",
    "slug": "will-bitcoin-reach-65000-by-december-31-2026-from-june-29",
    "market": "erreicht $65,000 bis 2027-01-01",
    "family": "touch",
    "side": "NO",
    "status": "OPEN",
    "tokenId": "40061706255869747632303223293656104479201110845197642951934190521166081913604",
    "entryTs": "2026-07-06T13:59:25Z",
    "entryPoly": 0.885,
    "entryFair": 0.8428,
    "entryEdgePP": -5.02,
    "shares": 869.57,
    "stakeUSD": 100.0,
    "realShares": 43.4783,
    "feePaid": 0.8,
    "wasNew": false
  },
  {
    "conditionId": "0xdaa4866bae18be58c5a79d2aeeffd035ec78f1bb49dbd88f72993997778a990f",
    "slug": "will-bitcoin-reach-100000-by-december-31-2026-571-361-361",
    "market": "erreicht $100,000 bis 2027-01-01",
    "family": "touch",
    "side": "NO",
    "status": "OPEN",
    "tokenId": "11291662904897713174667903388388696640643610556195928998276904135282270136756",
    "entryTs": "2026-07-06T13:59:25Z",
    "entryPoly": 0.105,
    "entryFair": 0.0729,
    "entryEdgePP": -3.95,
    "shares": 111.73,
    "stakeUSD": 100.0,
    "realShares": 5.5866,
    "feePaid": 0.73,
    "wasNew": false
  }
]