{
  "generatedAt": "2026-07-05T08:09:57Z",
  "summary": {
    "mode": "PAPER / DRY-RUN — kein echtes Geld",
    "totalPnl": -58.61,
    "realizedPnl": 235.24,
    "unrealizedPnl": -293.85,
    "openCount": 40,
    "closedCount": 5,
    "winRate": 0.8,
    "roiPct": 47.0,
    "stakedOpenUSD": 4000,
    "stakeUSD": 100.0,
    "edgeFloorPP": 2.5,
    "newMarketPnl": 15.73,
    "establishedPnl": -74.34,
    "newMarketCount": 4
  },
  "open": [
    {
      "market": "über $58,000 · 2026-07-11",
      "family": "above",
      "side": "NO",
      "entryPoly": 0.95,
      "markPoly": 0.935,
      "curEdgePP": -5.29,
      "entryEdgePP": -5.71,
      "unrealPnl": 29.65,
      "ageH": 15.6
    },
    {
      "market": "über $66,000 · 2026-07-09",
      "family": "above",
      "side": "NO",
      "entryPoly": 0.145,
      "markPoly": 0.12,
      "curEdgePP": -0.67,
      "entryEdgePP": -3.02,
      "unrealPnl": 1.9,
      "ageH": 14.1
    },
    {
      "market": "dip $40,000 bis 2027-01-01",
      "family": "touch",
      "side": "YES",
      "entryPoly": 0.23,
      "markPoly": 0.235,
      "curEdgePP": 5.64,
      "entryEdgePP": 6.83,
      "unrealPnl": 0.56,
      "ageH": 17.1
    },
    {
      "market": "über $64,000 · 2026-07-11",
      "family": "above",
      "side": "NO",
      "entryPoly": 0.4,
      "markPoly": 0.38,
      "curEdgePP": -4.57,
      "entryEdgePP": -3.9,
      "unrealPnl": 0.53,
      "ageH": 14.1
    },
    {
      "market": "erreicht $130,000 bis 2027-01-01",
      "family": "touch",
      "side": "NO",
      "entryPoly": 0.045,
      "markPoly": 0.04,
      "curEdgePP": -2.92,
      "entryEdgePP": -3.42,
      "unrealPnl": 0.2,
      "ageH": 17.1
    },
    {
      "market": "erreicht $150,000 bis 2027-01-01",
      "family": "touch",
      "side": "NO",
      "entryPoly": 0.032,
      "markPoly": 0.0305,
      "curEdgePP": -2.49,
      "entryEdgePP": -2.59,
      "unrealPnl": -0.07,
      "ageH": 17.1
    },
    {
      "market": "dip $47,500 bis 2026-08-01",
      "family": "touch",
      "side": "YES",
      "entryPoly": 0.045,
      "markPoly": 0.045,
      "curEdgePP": 2.94,
      "entryEdgePP": 2.62,
      "unrealPnl": -0.32,
      "ageH": 17.1
    },
    {
      "market": "erreicht $120,000 bis 2027-01-01",
      "family": "touch",
      "side": "NO",
      "entryPoly": 0.055,
      "markPoly": 0.055,
      "curEdgePP": -3.68,
      "entryEdgePP": -3.66,
      "unrealPnl": -0.39,
      "ageH": 17.1
    },
    {
      "market": "erreicht $140,000 bis 2027-01-01",
      "family": "touch",
      "side": "NO",
      "entryPoly": 0.035,
      "markPoly": 0.0375,
      "curEdgePP": -3.02,
      "entryEdgePP": -2.72,
      "unrealPnl": -0.51,
      "ageH": 17.1
    },
    {
      "market": "erreicht $110,000 bis 2027-01-01",
      "family": "touch",
      "side": "NO",
      "entryPoly": 0.075,
      "markPoly": 0.075,
      "curEdgePP": -3.83,
      "entryEdgePP": -3.94,
      "unrealPnl": -0.52,
      "ageH": 17.1
    },
    {
      "market": "dip $50,000 bis 2026-08-01",
      "family": "touch",
      "side": "YES",
      "entryPoly": 0.075,
      "markPoly": 0.075,
      "curEdgePP": 4.9,
      "entryEdgePP": 4.59,
      "unrealPnl": -0.53,
      "ageH": 17.1
    },
    {
      "market": "dip $35,000 bis 2027-01-01",
      "family": "touch",
      "side": "YES",
      "entryPoly": 0.125,
      "markPoly": 0.125,
      "curEdgePP": 9.18,
      "entryEdgePP": 9.44,
      "unrealPnl": -0.88,
      "ageH": 17.1
    },
    {
      "market": "dip $52,500 bis 2026-08-01",
      "family": "touch",
      "side": "YES",
      "entryPoly": 0.145,
      "markPoly": 0.145,
      "curEdgePP": 5.41,
      "entryEdgePP": 5.08,
      "unrealPnl": -1.02,
      "ageH": 17.1
    },
    {
      "market": "erreicht $72,500 bis 2026-08-01",
      "family": "touch",
      "side": "NO",
      "entryPoly": 0.135,
      "markPoly": 0.145,
      "curEdgePP": -2.94,
      "entryEdgePP": -3.34,
      "unrealPnl": -2.11,
      "ageH": 17.1
    },
    {
      "market": "dip $45,000 bis 2027-01-01",
      "family": "touch",
      "side": "YES",
      "entryPoly": 0.355,
      "markPoly": 0.355,
      "curEdgePP": 3.34,
      "entryEdgePP": 2.78,
      "unrealPnl": -2.48,
      "ageH": 14.1
    },
    {
      "market": "über $58,000 · 2026-07-09",
      "family": "above",
      "side": "NO",
      "entryPoly": 0.955,
      "markPoly": 0.956,
      "curEdgePP": -3.73,
      "entryEdgePP": -3.33,
      "unrealPnl": -2.54,
      "ageH": 17.1
    },
    {
      "market": "dip $50,000 bis 2027-01-01",
      "family": "touch",
      "side": "YES",
      "entryPoly": 0.505,
      "markPoly": 0.505,
      "curEdgePP": 1.15,
      "entryEdgePP": 0.99,
      "unrealPnl": -3.46,
      "ageH": 0.1
    },
    {
      "market": "über $66,000 · 2026-07-10",
      "family": "above",
      "side": "NO",
      "entryPoly": 0.13,
      "markPoly": 0.155,
      "curEdgePP": -2.79,
      "entryEdgePP": -2.52,
      "unrealPnl": -3.78,
      "ageH": 17.1
    },
    {
      "market": "dip $57,500 bis 2026-08-01",
      "family": "touch",
      "side": "YES",
      "entryPoly": 0.39,
      "markPoly": 0.385,
      "curEdgePP": 4.14,
      "entryEdgePP": 4.94,
      "unrealPnl": -4.01,
      "ageH": 17.1
    },
    {
      "market": "über $60,000 · 2026-07-11",
      "family": "above",
      "side": "NO",
      "entryPoly": 0.825,
      "markPoly": 0.83,
      "curEdgePP": -5.83,
      "entryEdgePP": -5.2,
      "unrealPnl": -4.09,
      "ageH": 15.6
    },
    {
      "market": "erreicht $70,000 bis 2026-08-01",
      "family": "touch",
      "side": "NO",
      "entryPoly": 0.255,
      "markPoly": 0.275,
      "curEdgePP": -4.75,
      "entryEdgePP": -4.77,
      "unrealPnl": -4.47,
      "ageH": 17.1
    },
    {
      "market": "über $64,000 · 2026-07-07",
      "family": "above",
      "side": "NO",
      "entryPoly": 0.285,
      "markPoly": 0.305,
      "curEdgePP": -4.21,
      "entryEdgePP": -4.34,
      "unrealPnl": -4.79,
      "ageH": 16.3
    },
    {
      "market": "dip $30,000 bis 2027-01-01",
      "family": "touch",
      "side": "YES",
      "entryPoly": 0.1,
      "markPoly": 0.095,
      "curEdgePP": 6.97,
      "entryEdgePP": 6.48,
      "unrealPnl": -5.7,
      "ageH": 17.1
    },
    {
      "market": "dip $55,000 bis 2026-08-01",
      "family": "touch",
      "side": "YES",
      "entryPoly": 0.255,
      "markPoly": 0.245,
      "curEdgePP": 4.04,
      "entryEdgePP": 3.5,
      "unrealPnl": -5.71,
      "ageH": 17.1
    },
    {
      "market": "über $64,000 · 2026-07-10",
      "family": "above",
      "side": "NO",
      "entryPoly": 0.32,
      "markPoly": 0.365,
      "curEdgePP": -3.88,
      "entryEdgePP": -3.17,
      "unrealPnl": -8.86,
      "ageH": 17.1
    },
    {
      "market": "erreicht $65,000 bis 2026-08-01",
      "family": "touch",
      "side": "NO",
      "entryPoly": 0.725,
      "markPoly": 0.745,
      "curEdgePP": -2.96,
      "entryEdgePP": -4.46,
      "unrealPnl": -9.2,
      "ageH": 17.1
    },
    {
      "market": "über $64,000 · 2026-07-09",
      "family": "above",
      "side": "NO",
      "entryPoly": 0.305,
      "markPoly": 0.355,
      "curEdgePP": -3.93,
      "entryEdgePP": -3.5,
      "unrealPnl": -9.32,
      "ageH": 17.1
    },
    {
      "market": "erreicht $67,500 bis 2026-08-01",
      "family": "touch",
      "side": "NO",
      "entryPoly": 0.435,
      "markPoly": 0.475,
      "curEdgePP": -6.38,
      "entryEdgePP": -5.07,
      "unrealPnl": -10.13,
      "ageH": 17.1
    },
    {
      "market": "über $62,000 · 2026-07-11",
      "family": "above",
      "side": "NO",
      "entryPoly": 0.605,
      "markPoly": 0.635,
      "curEdgePP": -5.54,
      "entryEdgePP": -3.65,
      "unrealPnl": -10.36,
      "ageH": 15.6
    },
    {
      "market": "über $64,000 · 2026-07-08",
      "family": "above",
      "side": "NO",
      "entryPoly": 0.275,
      "markPoly": 0.34,
      "curEdgePP": -4.41,
      "entryEdgePP": -3.0,
      "unrealPnl": -10.9,
      "ageH": 17.1
    },
    {
      "market": "über $62,000 · 2026-07-10",
      "family": "above",
      "side": "NO",
      "entryPoly": 0.61,
      "markPoly": 0.65,
      "curEdgePP": -6.06,
      "entryEdgePP": -5.73,
      "unrealPnl": -12.99,
      "ageH": 17.1
    },
    {
      "market": "über $62,000 · 2026-07-09",
      "family": "above",
      "side": "NO",
      "entryPoly": 0.61,
      "markPoly": 0.655,
      "curEdgePP": -5.04,
      "entryEdgePP": -4.67,
      "unrealPnl": -14.27,
      "ageH": 17.1
    },
    {
      "market": "über $58,000 · 2026-07-10",
      "family": "above",
      "side": "NO",
      "entryPoly": 0.935,
      "markPoly": 0.945,
      "curEdgePP": -5.02,
      "entryEdgePP": -3.47,
      "unrealPnl": -15.83,
      "ageH": 17.1
    },
    {
      "market": "über $62,000 · 2026-07-07",
      "family": "above",
      "side": "NO",
      "entryPoly": 0.65,
      "markPoly": 0.705,
      "curEdgePP": -4.9,
      "entryEdgePP": -4.35,
      "unrealPnl": -18.16,
      "ageH": 17.1
    },
    {
      "market": "über $60,000 · 2026-07-08",
      "family": "above",
      "side": "NO",
      "entryPoly": 0.885,
      "markPoly": 0.905,
      "curEdgePP": -5.45,
      "entryEdgePP": -4.25,
      "unrealPnl": -18.19,
      "ageH": 17.1
    },
    {
      "market": "über $62,000 · 2026-07-08",
      "family": "above",
      "side": "NO",
      "entryPoly": 0.62,
      "markPoly": 0.68,
      "curEdgePP": -5.38,
      "entryEdgePP": -4.02,
      "unrealPnl": -18.45,
      "ageH": 17.1
    },
    {
      "market": "über $60,000 · 2026-07-10",
      "family": "above",
      "side": "NO",
      "entryPoly": 0.815,
      "markPoly": 0.85,
      "curEdgePP": -6.25,
      "entryEdgePP": -3.71,
      "unrealPnl": -20.22,
      "ageH": 17.1
    },
    {
      "market": "über $60,000 · 2026-07-09",
      "family": "above",
      "side": "NO",
      "entryPoly": 0.845,
      "markPoly": 0.875,
      "curEdgePP": -5.63,
      "entryEdgePP": -3.92,
      "unrealPnl": -20.44,
      "ageH": 17.1
    },
    {
      "market": "über $60,000 · 2026-07-07",
      "family": "above",
      "side": "NO",
      "entryPoly": 0.91,
      "markPoly": 0.935,
      "curEdgePP": -6.17,
      "entryEdgePP": -2.71,
      "unrealPnl": -28.41,
      "ageH": 17.1
    },
    {
      "market": "über $62,000 · 2026-07-05",
      "family": "above",
      "side": "NO",
      "entryPoly": 0.895,
      "markPoly": 0.9505,
      "curEdgePP": -2.18,
      "entryEdgePP": -4.71,
      "unrealPnl": -53.59,
      "ageH": 16.3
    }
  ],
  "closed": [
    {
      "conditionId": "0x6811c0d6494cbe7a45cf1bde494add4e82a12e222715b71caef01c112865f120",
      "slug": "bitcoin-above-64k-on-july-6-2026",
      "market": "über $64,000 · 2026-07-06",
      "family": "above",
      "side": "NO",
      "status": "CLOSED",
      "entryTs": "2026-07-04T15:01:42Z",
      "entryPoly": 0.1805,
      "entryFair": 0.1508,
      "entryEdgePP": -4.23,
      "shares": 122.03,
      "stakeUSD": 100.0,
      "feePaid": 2.75,
      "markPoly": 0.1865,
      "curEdgePP": -3.74,
      "exitTs": "2026-07-05T08:03:35Z",
      "exitMark": 0.2125,
      "exitReason": "converged",
      "realizedPnl": -6.65,
      "roiPct": -6.7
    },
    {
      "conditionId": "0x357ef67b1d8665d64339f06f3b5c250aeb6294caf708f90cfc60a51f473c8f48",
      "slug": "bitcoin-above-64k-on-july-5-2026",
      "market": "über $64,000 · 2026-07-05",
      "family": "above",
      "side": "YES",
      "status": "CLOSED",
      "entryTs": "2026-07-04T15:01:42Z",
      "entryPoly": 0.0535,
      "entryFair": 0.0931,
      "entryEdgePP": 3.59,
      "shares": 1869.16,
      "stakeUSD": 100.0,
      "feePaid": 1.61,
      "markPoly": 0.0865,
      "curEdgePP": 2.91,
      "exitTs": "2026-07-04T18:06:11Z",
      "exitMark": 0.1775,
      "exitReason": "converged",
      "realizedPnl": 230.17,
      "roiPct": 230.2
    },
    {
      "conditionId": "0x28f59e8824137912266b5c8c6960ca458af9b963a5468ac6bc2d6ff05483bb91",
      "slug": "bitcoin-above-62k-on-july-6-2026",
      "market": "über $62,000 · 2026-07-06",
      "family": "above",
      "side": "YES",
      "status": "CLOSED",
      "entryTs": "2026-07-04T15:11:16Z",
      "entryPoly": 0.685,
      "entryFair": 0.7482,
      "entryEdgePP": 4.12,
      "shares": 145.99,
      "stakeUSD": 100.0,
      "feePaid": 3.99,
      "exitTs": "2026-07-04T15:52:02Z",
      "exitMark": 0.745,
      "exitReason": "converged",
      "realizedPnl": 4.77,
      "roiPct": 4.8
    },
    {
      "conditionId": "0xf43c98fc3069d7cd2ec2f1825c4e1285c6870d0cdf4989061930d8cc4555a03a",
      "slug": "bitcoin-above-62k-on-july-5-2026",
      "market": "über $62,000 · 2026-07-05",
      "family": "above",
      "side": "YES",
      "status": "CLOSED",
      "entryTs": "2026-07-04T15:11:16Z",
      "entryPoly": 0.835,
      "entryFair": 0.8847,
      "entryEdgePP": 3.81,
      "shares": 119.76,
      "stakeUSD": 100.0,
      "feePaid": 1.9,
      "exitTs": "2026-07-04T15:52:02Z",
      "exitMark": 0.895,
      "exitReason": "thesis_break",
      "realizedPnl": 5.29,
      "roiPct": 5.3
    },
    {
      "conditionId": "0x578327f87338039e1545315a124e3ace202fb8fa6bfbab58dba26616bdc1d47f",
      "slug": "bitcoin-above-60k-on-july-6-2026",
      "market": "über $60,000 · 2026-07-06",
      "family": "above",
      "side": "YES",
      "status": "CLOSED",
      "entryTs": "2026-07-04T15:11:16Z",
      "entryPoly": 0.945,
      "entryFair": 0.9768,
      "entryEdgePP": 2.79,
      "shares": 105.82,
      "stakeUSD": 100.0,
      "feePaid": 0.62,
      "exitTs": "2026-07-04T15:52:02Z",
      "exitMark": 0.9665,
      "exitReason": "converged",
      "realizedPnl": 1.66,
      "roiPct": 1.7
    }
  ],
  "activity": []
}