{
  "summary": {
    "enabled": true,
    "feedCount": 50,
    "walletsProbed": 12,
    "qualifiedCount": 2,
    "rejectedCount": 10,
    "avgCopyLagPP": -12.0,
    "lagSample": 2,
    "verdict": "Kopieren kostet im Schnitt -12.00pp pro Trade"
  },
  "wallets": [
    {
      "resolved": 7500,
      "uniqueMarkets": 1473,
      "roi": 9.8,
      "pnl": 18625580.0,
      "winRate": 57.5,
      "volume": 65773532.0,
      "inactiveDays": 1.7,
      "oneHit": false,
      "biggestWin": 593697.38,
      "qualified": true,
      "rejectReasons": [],
      "wallet": "0x204f72f35326db932158cba6adff0b9a1da95e14",
      "name": "0x204f72f3…",
      "firstTrade": "2026-06-13",
      "lastTrade": "2026-07-13"
    },
    {
      "resolved": 8116,
      "uniqueMarkets": 3155,
      "roi": 4.34,
      "pnl": 2208682.0,
      "winRate": 62.8,
      "volume": 22411263.0,
      "inactiveDays": 6.2,
      "oneHit": false,
      "biggestWin": 373139.17,
      "qualified": true,
      "rejectReasons": [],
      "wallet": "0x076daa87c4fe1a85402a9b6b8e0a866224388d4c",
      "name": "0x076daa87…",
      "firstTrade": "2026-06-04",
      "lastTrade": "2026-07-09"
    },
    {
      "resolved": 6,
      "uniqueMarkets": 13,
      "roi": 13.7,
      "pnl": 7087.28,
      "winRate": 66.7,
      "volume": 49661.0,
      "inactiveDays": 5.1,
      "oneHit": true,
      "biggestWin": 6302.43,
      "qualified": false,
      "rejectReasons": [
        "zu wenig Historie (6 aufgelöst)",
        "nur 13 Märkte",
        "Ein-Treffer-Wunder (89% des Gewinns aus 1 Trade)"
      ],
      "wallet": "0x060f34e5aa82cc11c2a54c9edf3e6a0632925a9d",
      "name": "0x060f34e5…",
      "firstTrade": "2026-07-09",
      "lastTrade": "2026-07-10"
    },
    {
      "resolved": 31,
      "uniqueMarkets": 157,
      "roi": 4.37,
      "pnl": 851.25,
      "winRate": 22.6,
      "volume": 11069.0,
      "inactiveDays": 19.0,
      "oneHit": false,
      "biggestWin": 175.76,
      "qualified": false,
      "rejectReasons": [
        "zu wenig Historie (31 aufgelöst)"
      ],
      "wallet": "0x90486d60a5f0027d21f2251d5459013792edd351",
      "name": "0x90486d60…",
      "firstTrade": "2026-06-10",
      "lastTrade": "2026-06-26"
    },
    {
      "resolved": 64,
      "uniqueMarkets": 141,
      "roi": 0.28,
      "pnl": 199.82,
      "winRate": 96.9,
      "volume": 103901.0,
      "inactiveDays": 57.0,
      "oneHit": true,
      "biggestWin": 3202.28,
      "qualified": false,
      "rejectReasons": [
        "Ein-Treffer-Wunder (1603% des Gewinns aus 1 Trade)",
        "inaktiv seit 57d"
      ],
      "wallet": "0x69e369c82246d861e18bb24bc425f7f5ba36761f",
      "name": "0x69e369c8…",
      "firstTrade": "2026-05-03",
      "lastTrade": "2026-05-19"
    },
    {
      "resolved": 4,
      "uniqueMarkets": 5,
      "roi": 0.2,
      "pnl": 2470.24,
      "winRate": 100.0,
      "volume": 966624.0,
      "inactiveDays": 3.3,
      "oneHit": false,
      "biggestWin": 1121.93,
      "qualified": false,
      "rejectReasons": [
        "zu wenig Historie (4 aufgelöst)",
        "nur 5 Märkte"
      ],
      "wallet": "0x66b58093676354bc03bf3a9ead97c230635b5bd9",
      "name": "0x66b58093…",
      "firstTrade": "2026-07-06",
      "lastTrade": "2026-07-12"
    },
    {
      "resolved": 50,
      "uniqueMarkets": 162,
      "roi": 0.03,
      "pnl": 8.01,
      "winRate": 78.0,
      "volume": 33741.0,
      "inactiveDays": 86.8,
      "oneHit": true,
      "biggestWin": 960.38,
      "qualified": false,
      "rejectReasons": [
        "Ein-Treffer-Wunder (11992% des Gewinns aus 1 Trade)",
        "inaktiv seit 87d"
      ],
      "wallet": "0x91d757346e322976a9544dd07b9b7e3f58550dfc",
      "name": "0x91d75734…",
      "firstTrade": "2026-04-05",
      "lastTrade": "2026-04-19"
    },
    {
      "resolved": 163,
      "uniqueMarkets": 369,
      "roi": -6.96,
      "pnl": -3812.93,
      "winRate": 69.3,
      "volume": 947197.0,
      "inactiveDays": 189.9,
      "oneHit": false,
      "biggestWin": 1182.07,
      "qualified": false,
      "rejectReasons": [
        "inaktiv seit 190d",
        "verliert Geld (ROI -7.0%)",
        "negatives PnL"
      ],
      "wallet": "0xe2831cc63e835eea242dce16d785db0011f97190",
      "name": "0xe2831cc6…",
      "firstTrade": "2025-10-27",
      "lastTrade": "2026-01-06"
    },
    {
      "resolved": 3655,
      "uniqueMarkets": 2536,
      "roi": -7.25,
      "pnl": -217740.86,
      "winRate": 46.4,
      "volume": 13326302.0,
      "inactiveDays": 0.5,
      "oneHit": false,
      "biggestWin": 14179.71,
      "qualified": false,
      "rejectReasons": [
        "verliert Geld (ROI -7.2%)",
        "negatives PnL"
      ],
      "wallet": "0x9e3ed7b661a903fc97afcf49e0f014ebe869f882",
      "name": "0x9e3ed7b6…",
      "firstTrade": "2026-07-09",
      "lastTrade": "2026-07-15"
    },
    {
      "resolved": 3,
      "uniqueMarkets": 7,
      "roi": -27.97,
      "pnl": -995.5,
      "winRate": 66.7,
      "volume": 5608.0,
      "inactiveDays": 176.7,
      "oneHit": false,
      "biggestWin": 114.66,
      "qualified": false,
      "rejectReasons": [
        "zu wenig Historie (3 aufgelöst)",
        "nur 7 Märkte",
        "inaktiv seit 177d",
        "verliert Geld (ROI -28.0%)",
        "negatives PnL"
      ],
      "wallet": "0x9187e0753f5d9bff3d943115a2aecb3bb7b5b2e1",
      "name": "0x9187e075…",
      "firstTrade": "2026-01-19",
      "lastTrade": "2026-01-19"
    },
    {
      "resolved": 50,
      "uniqueMarkets": 137,
      "roi": -32.48,
      "pnl": -5185.38,
      "winRate": 62.0,
      "volume": 482684.0,
      "inactiveDays": 207.3,
      "oneHit": false,
      "biggestWin": 475.64,
      "qualified": false,
      "rejectReasons": [
        "inaktiv seit 207d",
        "verliert Geld (ROI -32.5%)",
        "negatives PnL"
      ],
      "wallet": "0xe91171f655be1568e4c63f29663c0028649e3d4e",
      "name": "0xe91171f6…",
      "firstTrade": "2025-12-16",
      "lastTrade": "2025-12-20"
    },
    {
      "resolved": 2,
      "uniqueMarkets": 7,
      "roi": 0.0,
      "pnl": 4924.27,
      "winRate": 100.0,
      "volume": 3800.0,
      "inactiveDays": 0.1,
      "oneHit": true,
      "biggestWin": 3142.55,
      "qualified": false,
      "rejectReasons": [
        "zu wenig Historie (2 aufgelöst)",
        "nur 7 Märkte",
        "Ein-Treffer-Wunder (64% des Gewinns aus 1 Trade)",
        "verliert Geld (ROI 0.0%)"
      ],
      "wallet": "0x940063e955bbd7e9f44bd05dc750d3f0f2826ec0",
      "name": "Mrgivemeall",
      "firstTrade": "2026-07-15",
      "lastTrade": "2026-07-15"
    }
  ],
  "feed": [
    {
      "wallet": "0x66b58093676354bc03bf3a9ead97c230635b5bd9",
      "name": "0x66b58093…",
      "qualified": false,
      "market": "Will Gedion Timothewos be the next Prime Minister of Ethiopia?",
      "slug": "will-gedion-timothewos-be-the-next-prime-minister-of-ethiopia",
      "side": "SELL",
      "outcome": "Yes",
      "price": 0.002,
      "sizeUSD": 5200.0,
      "ts": "2026-07-15T15:39:16+00:00",
      "copyLagPP": null
    },
    {
      "wallet": "0x9e3ed7b661a903fc97afcf49e0f014ebe869f882",
      "name": "0x9e3ed7b6…",
      "qualified": false,
      "market": "Exact Score: England 3 - 2 Argentina?",
      "slug": "fifwc-eng-arg-2026-07-15-exact-score-3-2",
      "side": "BUY",
      "outcome": "Yes",
      "price": 0.0229999998,
      "sizeUSD": 4140.434781,
      "ts": "2026-07-15T15:36:13+00:00",
      "copyLagPP": null
    },
    {
      "wallet": "0x076daa87c4fe1a85402a9b6b8e0a866224388d4c",
      "name": "0x076daa87…",
      "qualified": true,
      "market": "Iasi Open: Anna Bondar vs Tamara Zidansek",
      "slug": "wta-bondar-zidanse-2026-07-15",
      "side": "BUY",
      "outcome": "Anna Bondar",
      "price": 0.6599999997,
      "sizeUSD": 2548.878786,
      "ts": "2026-07-15T15:36:13+00:00",
      "copyLagPP": -23.5
    },
    {
      "wallet": "0x69e369c82246d861e18bb24bc425f7f5ba36761f",
      "name": "0x69e369c8…",
      "qualified": false,
      "market": "England vs. Argentina: England O/U 0.5 AND England vs. Argentina: Team to Advance",
      "slug": null,
      "side": "BUY",
      "outcome": null,
      "price": 0.2708999998,
      "sizeUSD": 3561.535621,
      "ts": "2026-07-15T15:36:13+00:00",
      "copyLagPP": null
    },
    {
      "wallet": "0xe2831cc63e835eea242dce16d785db0011f97190",
      "name": "0xe2831cc6…",
      "qualified": false,
      "market": "Exact Score: England 3 - 3 Argentina?",
      "slug": "fifwc-eng-arg-2026-07-15-exact-score-3-3",
      "side": "BUY",
      "outcome": "Yes",
      "price": 0.011,
      "sizeUSD": 2727.272726,
      "ts": "2026-07-15T15:34:16+00:00",
      "copyLagPP": null
    },
    {
      "wallet": "0x9187e0753f5d9bff3d943115a2aecb3bb7b5b2e1",
      "name": "0x9187e075…",
      "qualified": false,
      "market": "Dota 2: 1win vs Vici Gaming (BO3) - Esports World Cup Survival",
      "slug": "dota2-1win-vg-2026-07-15",
      "side": "BUY",
      "outcome": "1win",
      "price": 0.91,
      "sizeUSD": 2527.472522,
      "ts": "2026-07-15T15:26:11+00:00",
      "copyLagPP": null
    },
    {
      "wallet": "0x91d757346e322976a9544dd07b9b7e3f58550dfc",
      "name": "0x91d75734…",
      "qualified": false,
      "market": "Bitcoin Up or Down on July 15?",
      "slug": "bitcoin-up-or-down-on-july-15-2026",
      "side": "BUY",
      "outcome": "Up",
      "price": 0.9849333183,
      "sizeUSD": 2658.0,
      "ts": "2026-07-15T15:26:08+00:00",
      "copyLagPP": null
    },
    {
      "wallet": "0x90486d60a5f0027d21f2251d5459013792edd351",
      "name": "0x90486d60…",
      "qualified": false,
      "market": "England vs. Argentina: Team to Advance",
      "slug": "fifwc-eng-arg-2026-07-15-more-markets",
      "side": "BUY",
      "outcome": "England",
      "price": 0.5399999996,
      "sizeUSD": 1111.11111,
      "ts": "2026-07-15T15:26:08+00:00",
      "copyLagPP": null
    },
    {
      "wallet": "0x2da325618fff9b2ffe64a49253fbcae8c7b9f258",
      "name": "0x2da32561…",
      "qualified": false,
      "market": "LoL: Movistar KOI vs GAM Esports (BO3) - Esports World Cup Group C",
      "slug": "lol-mkoi-gam-2026-07-15",
      "side": "BUY",
      "outcome": "GAM Esports",
      "price": 0.18,
      "sizeUSD": 1473.0,
      "ts": "2026-07-15T15:16:11+00:00",
      "copyLagPP": null
    },
    {
      "wallet": "0xf3ef6ac0510c9eabc42fbb146b5c3c64edc1ca6b",
      "name": "0xf3ef6ac0…",
      "qualified": false,
      "market": "LoL: Movistar KOI vs GAM Esports - Game 2 Winner",
      "slug": "lol-mkoi-gam-2026-07-15-game2",
      "side": "BUY",
      "outcome": "Movistar KOI",
      "price": 0.49,
      "sizeUSD": 1600.0,
      "ts": "2026-07-15T15:16:08+00:00",
      "copyLagPP": null
    },
    {
      "wallet": "0xc55082e391de438f294e5f3256c40fbdee84e090",
      "name": "0xc55082e3…",
      "qualified": false,
      "market": "Will Lando Norris be the 2026 F1 Drivers' Champion?",
      "slug": "will-lando-norris-be-the-2026-f1-drivers-champion",
      "side": "SELL",
      "outcome": "No",
      "price": 0.979,
      "sizeUSD": 1021.41,
      "ts": "2026-07-15T15:12:44+00:00",
      "copyLagPP": null
    },
    {
      "wallet": "0x2005d16a84ceefa912d4e380cd32e7ff827875ea",
      "name": "0x2005d16a…",
      "qualified": false,
      "market": "Iasi Open: Anna Bondar vs Tamara Zidansek",
      "slug": "wta-bondar-zidanse-2026-07-15",
      "side": "BUY",
      "outcome": "Anna Bondar",
      "price": 0.6022973487,
      "sizeUSD": 2051.06,
      "ts": "2026-07-15T15:12:44+00:00",
      "copyLagPP": null
    },
    {
      "wallet": "0xcff7b5922b9eb13fbdf2a1ff6f2541c095c62fb1",
      "name": "0xcff7b592…",
      "qualified": false,
      "market": "Spread: Universitatea Craiova CS (-1.5) AND Athens Open: Lilli Tagger vs Sara Bejlek AND Croatia Open: Luca Van Assche vs Titouan Droguet AND Los Angeles Sparks vs. Minnesota Lynx: O/U 181.5 AND Exact Score: England 0 - 0 Argentina?",
      "slug": null,
      "side": "BUY",
      "outcome": null,
      "price": 0.01,
      "sizeUSD": 1048.0,
      "ts": "2026-07-15T15:06:10+00:00",
      "copyLagPP": null
    },
    {
      "wallet": "0xf5198df69e13937a40d1c76d6f72d9aa067d906b",
      "name": "0xf5198df6…",
      "qualified": false,
      "market": "Croatia Open: Tomas Etcheverry vs Daniel Merida Aguilar",
      "slug": "atp-etcheve-aguilar-2026-07-15",
      "side": "BUY",
      "outcome": "Daniel Merida Aguilar",
      "price": 0.66,
      "sizeUSD": 10000.0,
      "ts": "2026-07-15T15:06:10+00:00",
      "copyLagPP": null
    },
    {
      "wallet": "0x97cb3a7cef8eb9f7e5c1b549be4bdcb77e4bc910",
      "name": "0x97cb3a7c…",
      "qualified": false,
      "market": "Will Iran announce withdrawal from MOU negotiations by July 24?",
      "slug": "will-iran-announce-withdrawal-from-mou-negotiations-by-july-24",
      "side": "BUY",
      "outcome": "Yes",
      "price": 0.1895955291,
      "sizeUSD": 1582.315788,
      "ts": "2026-07-15T14:59:16+00:00",
      "copyLagPP": null
    },
    {
      "wallet": "0x940063e955bbd7e9f44bd05dc750d3f0f2826ec0",
      "name": "0x940063e9…",
      "qualified": false,
      "market": "Bitcoin Up or Down - July 15, 10:55AM-11:00AM ET",
      "slug": "btc-updown-5m-1784127300",
      "side": "BUY",
      "outcome": "Up",
      "price": 0.2445652723,
      "sizeUSD": 1635.555184,
      "ts": "2026-07-15T14:59:14+00:00",
      "copyLagPP": null
    },
    {
      "wallet": "0x000c8cb93bb5fd4c9f292c6b4c5f7c021bb6bcf3",
      "name": "0x000c8cb9…",
      "qualified": false,
      "market": "World Cup: Goalkeeper to Score?",
      "slug": "world-cup-goalkeeper-to-score-20260607161409835",
      "side": "BUY",
      "outcome": "Yes",
      "price": 0.013,
      "sizeUSD": 1071.53846,
      "ts": "2026-07-15T14:56:07+00:00",
      "copyLagPP": null
    },
    {
      "wallet": "0xeb490d0534bb68b4c2ce139b219a728cd2c3693e",
      "name": "0xeb490d05…",
      "qualified": false,
      "market": "Will WTI Crude Oil (WTI) hit (HIGH) $95 in July?",
      "slug": "what-price-will-wti-hit-in-july-2026",
      "side": "BUY",
      "outcome": "No",
      "price": 0.8983779656,
      "sizeUSD": 3384.989514,
      "ts": "2026-07-15T14:56:07+00:00",
      "copyLagPP": null
    },
    {
      "wallet": "0xd78de5016c7d4dec963db4130b0778e48c7681e0",
      "name": "0xd78de501…",
      "qualified": false,
      "market": "Harry Kane: 1+ goals",
      "slug": "fifwc-eng-arg-2026-07-15-player-props",
      "side": "BUY",
      "outcome": "Yes",
      "price": 0.3799999999,
      "sizeUSD": 4897.078946,
      "ts": "2026-07-15T14:56:05+00:00",
      "copyLagPP": null
    },
    {
      "wallet": "0x204f72f35326db932158cba6adff0b9a1da95e14",
      "name": "0x204f72f3…",
      "qualified": true,
      "market": "Exact Score: England 3 - 3 Argentina?",
      "slug": "fifwc-eng-arg-2026-07-15-exact-score",
      "side": "BUY",
      "outcome": "No",
      "price": 0.99,
      "sizeUSD": 4116.989897,
      "ts": "2026-07-15T14:56:05+00:00",
      "copyLagPP": null
    },
    {
      "wallet": "0x54bab0bc94667af224e21528804d49c1b87e04e4",
      "name": "0x54bab0bc…",
      "qualified": false,
      "market": "Iasi Open: Anna Bondar vs Tamara Zidansek",
      "slug": "wta-bondar-zidanse-2026-07-15",
      "side": "SELL",
      "outcome": "Anna Bondar",
      "price": 0.4800978897,
      "sizeUSD": 10063.37,
      "ts": "2026-07-15T14:56:04+00:00",
      "copyLagPP": null
    },
    {
      "wallet": "0x84cfffc3f16dcc353094de30d4a45226eccd2f63",
      "name": "0x84cfffc3…",
      "qualified": false,
      "market": "England vs. Argentina: Both Teams to Score",
      "slug": "fifwc-eng-arg-2026-07-15-more-markets",
      "side": "BUY",
      "outcome": "Yes",
      "price": 0.53,
      "sizeUSD": 1848.81,
      "ts": "2026-07-15T14:54:13+00:00",
      "copyLagPP": null
    },
    {
      "wallet": "0x940063e955bbd7e9f44bd05dc750d3f0f2826ec0",
      "name": "0x940063e9…",
      "qualified": false,
      "market": "Bitcoin Up or Down - July 15, 10:45AM-10:50AM ET",
      "slug": "btc-updown-5m-1784126700",
      "side": "BUY",
      "outcome": "Up",
      "price": 0.3436920476,
      "sizeUSD": 1163.83257,
      "ts": "2026-07-15T14:46:08+00:00",
      "copyLagPP": null
    },
    {
      "wallet": "0x24816c037cdc2c9bd979e69d777541cf560a9b79",
      "name": "0x24816c03…",
      "qualified": false,
      "market": "Will the Fed decrease interest rates by 25 bps after the July 2026 meeting?",
      "slug": "fed-decision-in-july-181",
      "side": "SELL",
      "outcome": "No",
      "price": 0.996,
      "sizeUSD": 34677.75,
      "ts": "2026-07-15T14:46:07+00:00",
      "copyLagPP": null
    },
    {
      "wallet": "0xe91171f655be1568e4c63f29663c0028649e3d4e",
      "name": "0xe91171f6…",
      "qualified": false,
      "market": "ITF Granby: Rebecca Marino vs Mei Yamaguchi",
      "slug": "itf-marin-yamaguc-2026-07-14",
      "side": "BUY",
      "outcome": "Mei Yamaguchi",
      "price": 0.38,
      "sizeUSD": 2401.0,
      "ts": "2026-07-15T14:36:08+00:00",
      "copyLagPP": null
    },
    {
      "wallet": "0xe91171f655be1568e4c63f29663c0028649e3d4e",
      "name": "0xe91171f6…",
      "qualified": false,
      "market": "ITF Granby: Rebecca Marino vs Mei Yamaguchi",
      "slug": "itf-marin-yamaguc-2026-07-14",
      "side": "BUY",
      "outcome": "Mei Yamaguchi",
      "price": 0.3716131907,
      "sizeUSD": 3366.0,
      "ts": "2026-07-15T14:36:08+00:00",
      "copyLagPP": null
    },
    {
      "wallet": "0xe91171f655be1568e4c63f29663c0028649e3d4e",
      "name": "0xe91171f6…",
      "qualified": false,
      "market": "ITF Granby: Rebecca Marino vs Mei Yamaguchi",
      "slug": "itf-marin-yamaguc-2026-07-14",
      "side": "BUY",
      "outcome": "Mei Yamaguchi",
      "price": 0.38,
      "sizeUSD": 2086.0,
      "ts": "2026-07-15T14:36:08+00:00",
      "copyLagPP": null
    },
    {
      "wallet": "0x2518940d122e38d235d367ea4557eaff2796254f",
      "name": "0x2518940d…",
      "qualified": false,
      "market": "LoL: Team Secret  vs Karmine Corp - Game 1 Winner",
      "slug": "lol-ts-kc-2026-07-15-game1",
      "side": "SELL",
      "outcome": "Karmine Corp",
      "price": 0.7092537624,
      "sizeUSD": 1920.97,
      "ts": "2026-07-15T14:36:07+00:00",
      "copyLagPP": null
    },
    {
      "wallet": "0x060f34e5aa82cc11c2a54c9edf3e6a0632925a9d",
      "name": "0x060f34e5…",
      "qualified": false,
      "market": "ITF Granby: Rebecca Marino vs Mei Yamaguchi",
      "slug": "itf-marin-yamaguc-2026-07-14",
      "side": "BUY",
      "outcome": "Rebecca Marino",
      "price": 0.63,
      "sizeUSD": 2422.0,
      "ts": "2026-07-15T14:36:07+00:00",
      "copyLagPP": null
    },
    {
      "wallet": "0x060f34e5aa82cc11c2a54c9edf3e6a0632925a9d",
      "name": "0x060f34e5…",
      "qualified": false,
      "market": "ITF Granby: Rebecca Marino vs Mei Yamaguchi",
      "slug": "itf-marin-yamaguc-2026-07-14",
      "side": "BUY",
      "outcome": "Rebecca Marino",
      "price": 0.62,
      "sizeUSD": 4987.0,
      "ts": "2026-07-15T14:36:07+00:00",
      "copyLagPP": null
    },
    {
      "wallet": "0xeac22222ef8d2be457c00101a1a4e4925ec5dddc",
      "name": "0xeac22222…",
      "qualified": false,
      "market": "Valorant: Gen.G Esports vs ZETA DIVISION (BO3) - VCT Pacific Group Alpha",
      "slug": "val-geng-zeta2-2026-07-16",
      "side": "BUY",
      "outcome": "ZETA DIVISION",
      "price": 0.24,
      "sizeUSD": 11733.11,
      "ts": "2026-07-15T14:36:07+00:00",
      "copyLagPP": null
    },
    {
      "wallet": "0x60d825e58eae7c7c4d5538320111e8662c031b70",
      "name": "0x60d825e5…",
      "qualified": false,
      "market": "Will Gedion Timothewos be the next Prime Minister of Ethiopia?",
      "slug": "next-prime-minister-of-ethiopia",
      "side": "BUY",
      "outcome": "No",
      "price": 0.998,
      "sizeUSD": 5200.0,
      "ts": "2026-07-15T14:36:05+00:00",
      "copyLagPP": null
    },
    {
      "wallet": "0x2a69660046d7acc4ab204d7cc5ba78b0776cd2f7",
      "name": "0x2a696600…",
      "qualified": false,
      "market": "FC Malisheva vs. KF Vllaznia Shkodër: Both Teams to Score",
      "slug": "col-mal-vll-2026-07-15-more-markets",
      "side": "BUY",
      "outcome": "No",
      "price": 0.45,
      "sizeUSD": 2986.8,
      "ts": "2026-07-15T14:36:02+00:00",
      "copyLagPP": null
    },
    {
      "wallet": "0x30f891cc7ef02c536de1026acdcc95464127b824",
      "name": "0x30f891cc…",
      "qualified": false,
      "market": "England vs. Argentina: O/U 6.5",
      "slug": "fifwc-eng-arg-2026-07-15-total-6pt5",
      "side": "BUY",
      "outcome": "Under",
      "price": 0.99,
      "sizeUSD": 2000.0,
      "ts": "2026-07-15T14:29:13+00:00",
      "copyLagPP": null
    },
    {
      "wallet": "0x940063e955bbd7e9f44bd05dc750d3f0f2826ec0",
      "name": "0x940063e9…",
      "qualified": false,
      "market": "Bitcoin Up or Down - July 15, 10:25AM-10:30AM ET",
      "slug": "btc-updown-5m-1784125500",
      "side": "BUY",
      "outcome": "Up",
      "price": 0.1574408556,
      "sizeUSD": 1846.75,
      "ts": "2026-07-15T14:26:07+00:00",
      "copyLagPP": null
    },
    {
      "wallet": "0xb3d75835fd264d77ac48b497c03f6c554be5ebaa",
      "name": "0xb3d75835…",
      "qualified": false,
      "market": "Exact Score: England 2 - 2 Argentina?",
      "slug": "fifwc-eng-arg-2026-07-15-exact-score-2-2",
      "side": "BUY",
      "outcome": "Yes",
      "price": 0.0599999995,
      "sizeUSD": 1666.666665,
      "ts": "2026-07-15T14:26:07+00:00",
      "copyLagPP": null
    },
    {
      "wallet": "0x50bec18c474d9a1d18b3be72332441302375371b",
      "name": "0x50bec18c…",
      "qualified": false,
      "market": "Will Brooks Koepka win the 2026 The Open Championship?",
      "slug": "2026-the-open-championship-winner",
      "side": "BUY",
      "outcome": "Yes",
      "price": 0.008,
      "sizeUSD": 8055.0,
      "ts": "2026-07-15T14:26:04+00:00",
      "copyLagPP": null
    },
    {
      "wallet": "0x204f72f35326db932158cba6adff0b9a1da95e14",
      "name": "0x204f72f3…",
      "qualified": true,
      "market": "Exact Score: England 2 - 1 Argentina?",
      "slug": "fifwc-eng-arg-2026-07-15-exact-score-2-1",
      "side": "BUY",
      "outcome": "No",
      "price": 0.92,
      "sizeUSD": 2375.5,
      "ts": "2026-07-15T14:19:25+00:00",
      "copyLagPP": -0.5
    },
    {
      "wallet": "0xbd70eebd1374580d4fbbf0291f4b6fba44fdd270",
      "name": "0xbd70eebd…",
      "qualified": false,
      "market": "Will Elon Musk post 100-119 tweets from July 10 to July 17, 2026?",
      "slug": "elon-musk-of-tweets-july-10-july-17",
      "side": "BUY",
      "outcome": "Yes",
      "price": 0.007,
      "sizeUSD": 4012.71,
      "ts": "2026-07-15T14:16:04+00:00",
      "copyLagPP": null
    },
    {
      "wallet": "0xff121ba3ae93b1753f92deeff49220b0f7dbdf36",
      "name": "0xff121ba3…",
      "qualified": false,
      "market": "Will the price of Bitcoin be above $62,000 on July 16?",
      "slug": "bitcoin-above-on-july-16-2026",
      "side": "BUY",
      "outcome": "Yes",
      "price": 0.9869912948,
      "sizeUSD": 1013.18016,
      "ts": "2026-07-15T14:15:59+00:00",
      "copyLagPP": null
    },
    {
      "wallet": "0xf4020197086a05ebac5567ce33ffba7ba4dbce7a",
      "name": "0xf4020197…",
      "qualified": false,
      "market": "Swiss Open: Arthur Rinderknech vs Clement Tabur",
      "slug": "atp-rinderk-tabur-2026-07-15",
      "side": "BUY",
      "outcome": "Arthur Rinderknech",
      "price": 0.6984564145,
      "sizeUSD": 1685.88,
      "ts": "2026-07-15T14:15:59+00:00",
      "copyLagPP": null
    },
    {
      "wallet": "0xe9076a87c5ed90ef16e6fe6529c943baeca0cff6",
      "name": "0xe9076a87…",
      "qualified": false,
      "market": "Exact Score: England 0 - 3 Argentina?",
      "slug": "fifwc-eng-arg-2026-07-15-exact-score",
      "side": "BUY",
      "outcome": "Yes",
      "price": 0.014,
      "sizeUSD": 1360.0,
      "ts": "2026-07-15T14:15:56+00:00",
      "copyLagPP": null
    },
    {
      "wallet": "0x940063e955bbd7e9f44bd05dc750d3f0f2826ec0",
      "name": "0x940063e9…",
      "qualified": false,
      "market": "Bitcoin Up or Down - July 15, 10:05AM-10:10AM ET",
      "slug": "btc-updown-5m-1784124300",
      "side": "BUY",
      "outcome": "Down",
      "price": 0.3299999995,
      "sizeUSD": 1212.121211,
      "ts": "2026-07-15T14:06:05+00:00",
      "copyLagPP": null
    },
    {
      "wallet": "0x5596381f31b2d9fb4d50d16bb25c98dfeabb87e9",
      "name": "0x5596381f…",
      "qualified": false,
      "market": "Will Mohammad Khatami be head of state in Iran end of 2026?",
      "slug": "will-mohammad-khatami-be-head-of-state-in-iran-end-of-2026",
      "side": "BUY",
      "outcome": "Yes",
      "price": 0.002,
      "sizeUSD": 9774.86,
      "ts": "2026-07-15T14:06:05+00:00",
      "copyLagPP": null
    },
    {
      "wallet": "0x443339c0b1e939b4233b36fcfd97ed5020c29d34",
      "name": "0x443339c0…",
      "qualified": false,
      "market": "Exact Score: England 2 - 1 Argentina?",
      "slug": "fifwc-eng-arg-2026-07-15-exact-score-2-1",
      "side": "BUY",
      "outcome": "Yes",
      "price": 0.0899999992,
      "sizeUSD": 1067.777776,
      "ts": "2026-07-15T14:06:05+00:00",
      "copyLagPP": null
    },
    {
      "wallet": "0xb43787991f8bf7fa86295ed514c54d7fd606cfb3",
      "name": "0xb4378799…",
      "qualified": false,
      "market": "Exact Score: England 2 - 0 Argentina? AND Exact Score: FK Sutjeska Nikšić 1 - 0 Qairat FK?",
      "slug": null,
      "side": "BUY",
      "outcome": null,
      "price": 0.01,
      "sizeUSD": 1048.0,
      "ts": "2026-07-15T14:06:02+00:00",
      "copyLagPP": null
    },
    {
      "wallet": "0x23222038e8255625fff4fff060af8fff89833ede",
      "name": "0x23222038…",
      "qualified": false,
      "market": "Will the price of Bitcoin be above $62,000 on July 15?",
      "slug": "bitcoin-above-on-july-15-2026",
      "side": "SELL",
      "outcome": "Yes",
      "price": 0.999,
      "sizeUSD": 17000.0,
      "ts": "2026-07-15T14:06:02+00:00",
      "copyLagPP": null
    },
    {
      "wallet": "0x363cdad35c9ec1129c0bd3cd332d7c218ef09b0e",
      "name": "0x363cdad3…",
      "qualified": false,
      "market": "Exact Score: England 3 - 3 Argentina?",
      "slug": "fifwc-eng-arg-2026-07-15-exact-score",
      "side": "BUY",
      "outcome": "Yes",
      "price": 0.0109999999,
      "sizeUSD": 9090.909089,
      "ts": "2026-07-15T14:06:02+00:00",
      "copyLagPP": null
    },
    {
      "wallet": "0x6e021a82c12e01886444ab3e918114faaf11d70a",
      "name": "0x6e021a82…",
      "qualified": false,
      "market": "ODI Series Ireland vs West Indies, Women: Ireland vs West Indies",
      "slug": "crint-irl7-wst4-2026-07-15",
      "side": "BUY",
      "outcome": "West Indies",
      "price": 0.7335687401,
      "sizeUSD": 1076.01,
      "ts": "2026-07-15T14:05:59+00:00",
      "copyLagPP": null
    },
    {
      "wallet": "0x82aecafd82a39271a94a014737d451104bda3a84",
      "name": "0x82aecafd…",
      "qualified": false,
      "market": "England vs. Argentina: Team to Advance",
      "slug": "fifwc-eng-arg-2026-07-15-more-markets",
      "side": "BUY",
      "outcome": "Argentina",
      "price": 0.4624999998,
      "sizeUSD": 2096.497296,
      "ts": "2026-07-15T14:05:59+00:00",
      "copyLagPP": null
    }
  ],
  "generatedAt": "2026-07-15 15:46 UTC",
  "note": "Ehrliches Copy-Trading: Bilanz selbst nachgerechnet (nicht dem Leaderboard glauben), Ein-Treffer-Wunder/Inaktive/Verlierer gefiltert, und der Copy-Lag ausgewiesen — die Kosten, die entstehen, weil der Wal mit seiner Order den Preis selbst bewegt."
}